Workbook
Name Company: 'Guide '!$E$11
Name Country: 'Guide '!$E$12
Name Coy: 'Guide '!$E$11
Name Forecast_year_end: 'Guide '!$E$37
Name Historical_End_Date: 'Guide '!$E$35
Name Latestet_Historical_Year_End: 'Guide '!$E$31
Name Modeler: 'Guide '!$E$25
Name Month_in_period: 'Guide '!$E$34
Name Slicer_Year: #N/A
Name Version_1.0: 'Guide '!$E$23

Sheet Cover Page
C4: =Company -> BUA FOOD PLC
C27: ="Financial Model For "&Latestet_Historical_Year_End+1 & " to " &Forecast_year_end -> Financial Model For 2024 to 2028
D29: ="Modeler : " &Modeler -> Modeler : Raymond Balogun

Sheet Guide 
B1: =Company -> BUA FOOD PLC
B3: Guide
B7: Model Details
C8: This Section Contains general and Technical information about the company
C9: Company Information
D11: Name of the Company | E11: BUA FOOD PLC
D12: Business Location | E12: NIGERIA
D13: Industry | E13: FMCG
D14: Purpose | E14: Investment Decision
D15: Tickers Symbol | E15: BUAFOODS
C17: Model Information
D19: Model Owner | E19: Investment Community
D20: Circularity Togo
D21: Interation Togo
D22: Currency | E22: =_xlfn.UNICHAR(8358) -> ₦
D23: Version | E23: version 1.0
D24: Latest Update
D25: Current Modeler | E25: Raymond Balogun
B27: Model Structure and Navigation
C28: This sections Highlight the Structure and Navigation in the Model
C29: Model Timing
D31: Lastest Historical Year End | E31: 2023
D32: Model Start Date | E32: =E35+1 -> 45292
D33: Model ForeCast | E33: 5
D34: Month in a period | E34: 12
D35: Historical End Date | E35: =DATE(E31,12,31) -> 45291
D36: Forecast End Date | E36: =DATE(E37,12,31) -> 47118
D37: Forecast End Year | E37: =E31+E33 -> 2028
C39: Sheet Structure
D41: Cover Page
D42: Guide
D43: Dashboard
D44: Model
D45: Historical & Restructuring
D46: Income Statement
D47: Financial position
D48: Cash Flow Statement
D49: DCF
D50: Calculations
D51: Inputs
B53: Model Style Guide
C54: This sections Contains the Style used in the Model
C55: Cell Style Guide
D56: Normal Cell | E56: 1234
D57: input Cells | E57: 12345
D58: linked Cells | E58: 12345
D59: Formular Cells | E59: 12345
D60: Historical Cells | E60: 12345
D61: Percentage Cells | E61: 0.2
D62: Total | E62: 12345
D64: Sub Total | E64: 12345
D65: Multiple | E65: 2.1
D66: Explanatory | E66: Explanatory
D67: Title cell | E67: Title Cell
D68: Sub- Title Cell | E68: Sub - Title
D69: Heading 1 | E69: Heading 1
D70: Heading 2 | E70: Heading 2
D71: Heading 3 | E71: Heading 3
D73: Table Header | E73: Table Header
B75: Glossary
C76: This Sections Contains Key Terms used in the model
C77: Key term
D78: Terms | E78: Description
D79: EBIT | E79: Earnings Before Interest and Tax
D80: EBITDA | E80: Earnings Before Interest Tax Depreciation and Amortization
D81: EBT | E81: Earnings Before Tax
D82: DCF | E82: Discounted Cash Flow
D83: IS | E83: Income Statement
D84: FP | E84: Financial Postion
D85: CF | E85: Cash Flow

Sheet Dashboard
A1: =Company -> BUA FOOD PLC

Sheet Model
A1: =Company -> BUA FOOD PLC
B3: Model
C5: Live Case : | I5: Start Date | L5: =K6+1 -> 44197 | M5: =L6+1 -> 44562 | N5: =M6+1 -> 44927 | O5: =N6+1 -> 45292 | P5: =O6+1 -> 45658 | Q5: =P6+1 -> 46023 | R5: =Q6+1 -> 46388 | S5: =R6+1 -> 46753
C6: Model Check : Ok | I6: End Date | K6: =EDATE(L6,-Month_in_period) -> 44196 | L6: =EDATE(M6,-Month_in_period) -> 44561 | M6: =EDATE(N6,-Month_in_period) -> 44926 | N6: =Historical_End_Date -> 45291 | O6: =EDATE(N6,Month_in_period) -> 45657 | P6: =EDATE(O6,Month_in_period) -> 46022 | Q6: =EDATE(P6,Month_in_period) -> 46387 | R6: =EDATE(Q6,Month_in_period) -> 46752 | S6: =EDATE(R6,Month_in_period) -> 47118
I7: Year | L7: =YEAR(L6) -> 2021 | M7: =YEAR(M6) -> 2022 | N7: =YEAR(N6) -> 2023 | O7: =YEAR(O6) -> 2024 | P7: =YEAR(P6) -> 2025 | Q7: =YEAR(Q6) -> 2026 | R7: =YEAR(R6) -> 2027 | S7: =YEAR(S6) -> 2028
I8: Year Counter | L8: =M8-1 -> -2 | M8: =N8-1 -> -1 | N8: 0 | O8: =N8+1 -> 1 | P8: =O8+1 -> 2 | Q8: =P8+1 -> 3 | R8: =Q8+1 -> 4 | S8: =R8+1 -> 5
D9: Description | E9: Unit
B10: Income Statement
C11: Revenue from contracts with customers | E11: [#'000] | L11: =Hist!L86 -> 333272234 | M11: =Hist!M86 -> 418347770 | N11: =Hist!N86 -> 729443355 | O11: =Cal!O17 -> 1.6047754e+09 | P11: =Cal!P17 -> 3.5305058e+09 | Q11: =Cal!Q17 -> 6.7079611e+09 | R11: =Cal!R17 -> 1.2745126e+10 | S11: =Cal!S17 -> 2.421574e+10
C12: Cost of sales | E12: [#'000] | L12: =Hist!L87 -> -224775825 | M12: =Hist!M87 -> -280694270 | N12: =Hist!N87 -> -462818283 | O12: =-Cal!O18 -> -1.235677e+09 | P12: =-Cal!P18 -> -2.7184895e+09 | Q12: =-Cal!Q18 -> -4.8968116e+09 | R12: =-Cal!R18 -> -9.303942e+09 | S12: =-Cal!S18 -> -1.767749e+10
C13: Gross profit | L13: =SUM(L11:L12) -> 108496409 | M13: =SUM(M11:M12) -> 137653500 | N13: =SUM(N11:N12) -> 266625072 | O13: =SUM(O11:O12) -> 3.6909834e+08 | P13: =SUM(P11:P12) -> 8.1201634e+08 | Q13: =SUM(Q11:Q12) -> 1.8111495e+09 | R13: =SUM(R11:R12) -> 3.441184e+09 | S13: =SUM(S11:S12) -> 6.5382497e+09
C15: Administrative expenses | E15: [#'000] | L15: =Hist!L90 -> -11757023 | M15: =Hist!M90 -> -15413481 | N15: =Hist!N90 -> -13976642 | O15: =-Cal!O32 -> -35305058 | P15: =-Cal!P32 -> -77671128 | Q15: =-Cal!Q32 -> -1.4757514e+08 | R15: =-Cal!R32 -> -2.8039277e+08 | S15: =-Cal!S32 -> -5.3274627e+08
C16: Selling and distribution expenses | E16: [#'000] | L16: =Hist!L91 -> -10135699 | M16: =Hist!M91 -> -14185483 | N16: =Hist!N91 -> -29849296 | O16: =-Cal!O33 -> -67400566 | P16: =-Cal!P33 -> -1.4828125e+08 | Q16: =-Cal!Q33 -> -2.8173437e+08 | R16: =-Cal!R33 -> -5.352953e+08 | S16: =-Cal!S33 -> -1.0170611e+09
C17: Net impairment writeback on financial assets | E17: [#'000] | L17: =Hist!L92 -> 143283 | M17: =Hist!M92 -> 2376501 | N17: =Hist!N92 -> -7890845 | O17: =Cal!O34 -> -7890845 | P17: =Cal!P34 -> -7890845 | Q17: =Cal!Q34 -> -7890845 | R17: =Cal!R34 -> -7890845 | S17: =Cal!S34 -> -7890845
C18: Other income | E18: [#'000] | L18: =Hist!L93 -> 1554540 | M18: =Hist!M93 -> 15242660 | N18: =Hist!N93 -> 809325 | O18: =Cal!O35 -> 40119385 | P18: =Cal!P35 -> 88262646 | Q18: =Cal!Q35 -> 1.6769903e+08 | R18: =Cal!R35 -> 3.1862815e+08 | S18: =Cal!S35 -> 6.0539349e+08
C19: EBITDA | E19: [#'000] | L19: =SUM(L13:L18) -> 88301510 | M19: =SUM(M13:M18) -> 125673697 | N19: =SUM(N13:N18) -> 215717614 | O19: =SUM(O13:O18) -> 2.9862125e+08 | P19: =SUM(P13:P18) -> 6.6643577e+08 | Q19: =SUM(Q13:Q18) -> 1.5416482e+09 | R19: =SUM(R13:R18) -> 2.9362333e+09 | S19: =SUM(S13:S18) -> 5.585945e+09
C21: Depreciation | E21: [#'000] | L21: =Hist!L96 -> -8406635 | M21: =Hist!M96 -> -8181404 | N21: =Hist!N96 -> -9401495 | O21: =Cal!O51 -> -9486784.3 | P21: =Cal!P51 -> -10373799 | Q21: =Cal!Q51 -> -11343749 | R21: =Cal!R51 -> -12404389 | S21: =Cal!S51 -> -13564200
C22: EBIT | E22: [#'000] | L22: =SUM(L19:L21) -> 79894875 | M22: =SUM(M19:M21) -> 117492293 | N22: =SUM(N19:N21) -> 206316119 | O22: =SUM(O19:O21) -> 2.8913447e+08 | P22: =SUM(P19:P21) -> 6.5606197e+08 | Q22: =SUM(Q19:Q21) -> 1.5303044e+09 | R22: =SUM(R19:R21) -> 2.9238289e+09 | S22: =SUM(S19:S21) -> 5.5723808e+09
C24: Finance Income | E24: [#'000] | L24: =Hist!L99 -> 2892019 | M24: =Hist!M99 -> 39721 | N24: =Hist!N99 -> 2497371 | O24: =Cal!O36 -> 2497371 | P24: =Cal!P36 -> 2497371 | Q24: =Cal!Q36 -> 2497371 | R24: =Cal!R36 -> 2497371 | S24: =Cal!S36 -> 2497371
C25: Finance Cost | E25: [#'000] | L25: =Hist!L100 -> -5047646 | M25: =Hist!M100 -> -8721781 | N25: =Hist!N100 -> -100678918 | O25: =Cal!O37 -> -100678918 | P25: =Cal!P37 -> -100678918 | Q25: =Cal!Q37 -> -100678918 | R25: =Cal!R37 -> -100678918 | S25: =Cal!S37 -> -100678918
C26: EBT | E26: [#'000] | L26: =SUM(L22:L25) -> 77739248 | M26: =SUM(M22:M25) -> 108810233 | N26: =SUM(N22:N25) -> 108134572 | O26: =SUM(O22:O25) -> 1.9095292e+08 | P26: =SUM(P22:P25) -> 5.5788042e+08 | Q26: =SUM(Q22:Q25) -> 1.4321229e+09 | R26: =SUM(R22:R25) -> 2.8256473e+09 | S26: =SUM(S22:S25) -> 5.4741992e+09
C28: Minimum tax | E28: [#'000] | L28: =Hist!L103 -> -270527 | M28: =Hist!M103 -> -1580531 | N28: =Hist!N103 -> -10640 | O28: =Cal!O38 -> -10640 | P28: =Cal!P38 -> -10640 | Q28: =Cal!Q38 -> -10640 | R28: =Cal!R38 -> -10640 | S28: =Cal!S38 -> -10640
C29: Income and deferred tax expense | E29: [#'000] | L29: =Hist!L104 -> -7700636 | M29: =Hist!M104 -> -15885683 | N29: =Hist!N104 -> 3973565 | O29: =-Cal!O41 -> -11457175 | P29: =-Cal!P41 -> -33472825 | Q29: =-Cal!Q41 -> -85927372 | R29: =-Cal!R41 -> -1.6953884e+08 | S29: =-Cal!S41 -> -3.2845195e+08
C30: Net Earnings | E30: [#'000] | L30: =SUM(L26:L29) -> 69768085 | M30: =SUM(M26:M29) -> 91344019 | N30: =SUM(N26:N29) -> 112097497 | O30: =SUM(O26:O29) -> 1.7948511e+08 | P30: =SUM(P26:P29) -> 5.2439696e+08 | Q30: =SUM(Q26:Q29) -> 1.3461849e+09 | R30: =SUM(R26:R29) -> 2.6560979e+09 | S30: =SUM(S26:S29) -> 5.1457366e+09
B33: Financial Position
C35: Assets | L35: =IF(L49=L80,"OK","Not OK") -> OK | M35: =IF(M49=M80,"OK","Not OK") -> OK | N35: =IF(N49=N80,"OK","Not OK") -> OK | O35: =IF(O49=O80,"OK","Not OK") -> OK | P35: =IF(P49=P80,"OK","Not OK") -> OK | Q35: =IF(Q49=Q80,"OK","Not OK") -> OK | R35: =IF(R49=R80,"OK","Not OK") -> OK | S35: =IF(S49=S80,"OK","Not OK") -> OK
D36: Non-current assets
D37: Property, plant and equipment | E37: [#'000] | L37: =Hist!L38 -> 321675653 | M37: =Hist!M38 -> 330523752 | N37: =Hist!N38 -> 357991862 | O37: =Cal!O52 -> 3.914641e+08 | P37: =Cal!P52 -> 4.2806599e+08 | Q37: =Cal!Q52 -> 4.6809017e+08 | R37: =Cal!R52 -> 5.118566e+08 | S37: =Cal!S52 -> 5.5971519e+08
D38: Other Non- Current Assets | E38: [#'000] | L38: =Hist!L176 -> 1580361 | M38: =Hist!M176 -> 31165 | N38: =Hist!N176 -> 30324 | O38: =Cal!O55 -> 30324 | P38: =Cal!P55 -> 30324 | Q38: =Cal!Q55 -> 30324 | R38: =Cal!R55 -> 30324 | S38: =Cal!S55 -> 30324
D40: Total non-current assets | E40: [#'000] | L40: =SUM(L37:L39) -> 323256014 | M40: =SUM(M37:M39) -> 330554917 | N40: =SUM(N37:N39) -> 358022186 | O40: =SUM(O37:O39) -> 3.9149443e+08 | P40: =SUM(P37:P39) -> 4.2809632e+08 | Q40: =SUM(Q37:Q39) -> 4.6812049e+08 | R40: =SUM(R37:R39) -> 5.1188692e+08 | S40: =SUM(S37:S39) -> 5.5974551e+08
D41: Current assets
D42: Inventories | E42: [#'000] | L42: =Hist!L45 -> 24926471 | M42: 29760594 | N42: 112276641 | O42: =Cal!O92 -> 1.7604166e+08 | P42: =Cal!P92 -> 3.8729165e+08 | Q42: =Cal!Q92 -> 6.9762795e+08 | R42: =Cal!R92 -> 1.3254931e+09 | S42: =Cal!S92 -> 2.5184369e+09
D43: Trade receivables | E43: [#'000] | L43: =Hist!L182 -> 48967807 | M43: =Hist!M182 -> 107578798 | N43: =Hist!N182 -> 146000193 | O43: =Cal!O93 -> 2.6379869e+08 | P43: =Cal!P93 -> 5.8035712e+08 | Q43: =Cal!Q93 -> 1.1026785e+09 | R43: =Cal!R93 -> 2.0950892e+09 | S43: =Cal!S93 -> 3.9806695e+09
D44: Other assets | E44: [#'000] | L44: =Hist!L187 -> 3192269 | M44: =Hist!M187 -> 11746718 | N44: =Hist!N187 -> 5155922 | O44: =Cal!O109 -> 5155922 | P44: =Cal!P109 -> 5155922 | Q44: =Cal!Q109 -> 5155922 | R44: =Cal!R109 -> 5155922 | S44: =Cal!S109 -> 5155922
D45: Cash and balances with banks | E45: [#'000] | L45: =Hist!L47 -> 30338785 | M45: =Hist!M47 -> 32163428 | N45: =Hist!N47 -> 100124789 | O45: =CF!O32 -> 4.669523e+08 | P45: =CF!P32 -> 6.8136521e+08 | Q45: =CF!Q32 -> 9.579008e+08 | R45: =CF!R32 -> 1.232961e+09 | S45: =CF!S32 -> 1.4989207e+09
D46: Due from related parties | E46: [#'000] | L46: =Hist!L48 -> 162788169 | M46: =Hist!M48 -> 95420170 | N46: =Hist!N48 -> 348860131 | O46: =Cal!O110 -> 348860131 | P46: =Cal!P110 -> 348860131 | Q46: =Cal!Q110 -> 348860131 | R46: =Cal!R110 -> 348860131 | S46: =Cal!S110 -> 348860131
D47: Total current assets | E47: [#'000] | L47: =SUM(L42:L46) -> 270213501 | M47: =SUM(M42:M46) -> 276669708 | N47: =SUM(N42:N46) -> 712417676 | O47: =SUM(O42:O46) -> 1.2608087e+09 | P47: =SUM(P42:P46) -> 2.00303e+09 | Q47: =SUM(Q42:Q46) -> 3.1122233e+09 | R47: =SUM(R42:R46) -> 5.0075594e+09 | S47: =SUM(S42:S46) -> 8.3520432e+09
D49: Total assets | E49: [#'000] | L49: =L40+L47 -> 593469515 | M49: =M40+M47 -> 607224625 | N49: =N40+N47 -> 1070439862 | O49: =O40+O47 -> 1.6523031e+09 | P49: =P40+P47 -> 2.4311264e+09 | Q49: =Q40+Q47 -> 3.5803438e+09 | R49: =R40+R47 -> 5.5194463e+09 | S49: =S40+S47 -> 8.9117887e+09
C51: Equity
D52: Equity
D53: Share capital | E53: [#'000] | L53: =Hist!L55 -> 9000000 | M53: =Hist!M55 -> 9000000 | N53: =Hist!N55 -> 9000000 | O53: =Cal!O61 -> 9000000 | P53: =Cal!P61 -> 9000000 | Q53: =Cal!Q61 -> 9000000 | R53: =Cal!R61 -> 9000000 | S53: =Cal!S61 -> 9000000
D54: Reorganisation reserves | E54: [#'000] | L54: =Hist!L56 -> -943228 | M54: =Hist!M56 -> -943228 | N54: =Hist!N56 -> -943228 | O54: =Cal!O79 -> -943228 | P54: =Cal!P79 -> -943228 | Q54: =Cal!Q79 -> -943228 | R54: =Cal!R79 -> -943228 | S54: =Cal!S79 -> -943228
D55: Retained earnings | E55: [#'000] | L55: =Hist!L57 -> 192661901 | M55: =Hist!M57 -> 222904565 | N55: =Hist!N57 -> 254002062 | O55: =Cal!O76 -> 3.0784759e+08 | P55: =Cal!P76 -> 4.6516668e+08 | Q55: =Cal!Q76 -> 8.6902214e+08 | R55: =Cal!R76 -> 1.6658515e+09 | S55: =Cal!S76 -> 3.2095725e+09
D56: Total equity | E56: [#'000] | L56: =SUM(L53:L55) -> 200718673 | M56: =SUM(M53:M55) -> 230961337 | N56: =SUM(N53:N55) -> 262058834 | O56: =SUM(O53:O55) -> 3.1590437e+08 | P56: =SUM(P53:P55) -> 4.7322345e+08 | Q56: =SUM(Q53:Q55) -> 8.7707891e+08 | R56: =SUM(R53:R55) -> 1.6739083e+09 | S56: =SUM(S53:S55) -> 3.2176293e+09
D58: Liabilities
D59: Non-current liabilities
D60: Deferred tax liabilities | E60: [#'000] | L60: =Hist!L62 -> 15225186 | M60: =Hist!M62 -> 33776943 | N60: =Hist!N62 -> 22306746 | O60: =Cal!O113 -> 22306746 | P60: =Cal!P113 -> 22306746 | Q60: =Cal!Q113 -> 22306746 | R60: =Cal!R113 -> 22306746 | S60: =Cal!S113 -> 22306746
D61: Borrowings | E61: [#'000] | L61: =Hist!L63 -> 4889870 | M61: =Hist!M63 -> 3475257 | N61: =Hist!N63 -> 1377286 | O61: =Cal!O114 -> 1377286 | P61: =Cal!P114 -> 1377286 | Q61: =Cal!Q114 -> 1377286 | R61: =Cal!R114 -> 1377286 | S61: =Cal!S114 -> 1377286
D62: Lease liabilities | E62: [#'000] | L62: =Hist!L64 -> 33611 | M62: =Hist!M64 -> 32678 | N62: =Hist!N64 -> 32650 | O62: =Cal!O115 -> 32650 | P62: =Cal!P115 -> 32650 | Q62: =Cal!Q115 -> 32650 | R62: =Cal!R115 -> 32650 | S62: =Cal!S115 -> 32650
D63: Government grants | E63: [#'000] | L63: =Hist!L65 -> 0 | M63: =Hist!M65 -> 206665 | N63: =Hist!N65 -> 70211 | O63: =Cal!O116 -> 70211 | P63: =Cal!P116 -> 70211 | Q63: =Cal!Q116 -> 70211 | R63: =Cal!R116 -> 70211 | S63: =Cal!S116 -> 70211
D64: Deposit for shares | E64: [#'000] | L64: =Hist!L66 -> 32243723 | M64: =Hist!M66 -> 32243723 | N64: =Hist!N66 -> 0 | O64: =Cal!O117 -> 0 | P64: =Cal!P117 -> 0 | Q64: =Cal!Q117 -> 0 | R64: =Cal!R117 -> 0 | S64: =Cal!S117 -> 0
D65: Total non-current liabilities | E65: [#'000] | L65: =SUM(L60:L64) -> 52392390 | M65: =SUM(M60:M64) -> 69735266 | N65: =SUM(N60:N64) -> 23786893 | O65: =SUM(O60:O64) -> 23786893 | P65: =SUM(P60:P64) -> 23786893 | Q65: =SUM(Q60:Q64) -> 23786893 | R65: =SUM(R60:R64) -> 23786893 | S65: =SUM(S60:S64) -> 23786893
D67: Current liabilities
D68: Contract liabilites | E68: [#'000] | L68: =Hist!L70 -> 40931459 | M68: =Hist!M70 -> 47139328 | N68: =Hist!N70 -> 68950583 | O68: =Cal!O120 -> 68950583 | P68: =Cal!P120 -> 68950583 | Q68: =Cal!Q120 -> 68950583 | R68: =Cal!R120 -> 68950583 | S68: =Cal!S120 -> 68950583
D69: Current income tax payable | E69: [#'000] | L69: =Hist!L71 -> 12778745 | M69: =Hist!M71 -> 8323257 | N69: =Hist!N71 -> 15819889 | O69: =Cal!O121 -> 15819889 | P69: =Cal!P121 -> 15819889 | Q69: =Cal!Q121 -> 15819889 | R69: =Cal!R121 -> 15819889 | S69: =Cal!S121 -> 15819889
D70: Lease liabilities | E70: [#'000] | L70: =Hist!L72 -> 4292441 | M70: =Hist!M72 -> 5073 | N70: =Hist!N72 -> 5073 | O70: =Cal!O122 -> 5073 | P70: =Cal!P122 -> 5073 | Q70: =Cal!Q122 -> 5073 | R70: =Cal!R122 -> 5073 | S70: =Cal!S122 -> 5073
D71: Bank overdraft | E71: [#'000] | L71: =Hist!L73 -> 2851413 | M71: =Hist!M73 -> 4490873 | N71: =Hist!N73 -> 573175 | O71: =Cal!O123 -> 573175 | P71: =Cal!P123 -> 573175 | Q71: =Cal!Q123 -> 573175 | R71: =Cal!R123 -> 573175 | S71: =Cal!S123 -> 573175
D72: Borrowings | E72: [#'000] | L72: =Hist!L74 -> 241159110 | M72: =Hist!M74 -> 208195755 | N72: =Hist!N74 -> 649699556 | O72: =Cal!O67 -> 1007141199 | P72: =Cal!P67 -> 1364582842 | Q72: =Cal!Q67 -> 1722024485 | R72: =Cal!R67 -> 2079466128 | S72: =Cal!S67 -> 2436907771
D73: Due to related parties | E73: [#'000] | L73: =Hist!L75 -> 0 | M73: =Hist!M75 -> 0 | N73: =Hist!N75 -> 0 | O73: =Cal!O124 -> 0 | P73: =Cal!P124 -> 0 | Q73: =Cal!Q124 -> 0 | R73: =Cal!R124 -> 0 | S73: =Cal!S124 -> 0
D74: Trade and other payables | E74: [#'000] | L74: =Hist!L76 -> 38345284 | M74: =Hist!M76 -> 38325101 | N74: =Hist!N76 -> 49475977 | O74: =Cal!O94 -> 2.2005208e+08 | P74: =Cal!P94 -> 4.8411457e+08 | Q74: =Cal!Q94 -> 8.7203494e+08 | R74: =Cal!R94 -> 1.6568664e+09 | S74: =Cal!S94 -> 3.1480461e+09
D75: Government grants | E75: [#'000] | L75: =Hist!L77 -> 0 | M75: =Hist!M77 -> 48635 | N75: =Hist!N77 -> 69882 | O75: {=Cal!O125} -> 69882 | P75: 69882 | Q75: 69882 | R75: 69882 | S75: 69882
D76: Total current liabilities | E76: [#'000] | L76: =SUM(L68:L75) -> 340358452 | M76: =SUM(M68:M75) -> 306528022 | N76: =SUM(N68:N75) -> 784594135 | O76: =SUM(O68:O75) -> 1.3126119e+09 | P76: =SUM(P68:P75) -> 1.934116e+09 | Q76: =SUM(Q68:Q75) -> 2.679478e+09 | R76: =SUM(R68:R75) -> 3.8217511e+09 | S76: =SUM(S68:S75) -> 5.6703725e+09
D78: Total liabilities | E78: [#'000] | L78: =L65+L76 -> 392750842 | M78: =M65+M76 -> 376263288 | N78: =N65+N76 -> 808381028 | O78: =O65+O76 -> 1.3363988e+09 | P78: =P65+P76 -> 1.9579029e+09 | Q78: =Q65+Q76 -> 2.7032649e+09 | R78: =R65+R76 -> 3.845538e+09 | S78: =S65+S76 -> 5.6941594e+09
D80: Total equity and liabilities | E80: [#'000] | L80: =L78+L56 -> 593469515 | M80: =M78+M56 -> 607224625 | N80: =N78+N56 -> 1070439862 | O80: =O78+O56 -> 1.6523031e+09 | P80: =P78+P56 -> 2.4311264e+09 | Q80: =Q78+Q56 -> 3.5803438e+09 | R80: =R78+R56 -> 5.5194463e+09 | S80: =S78+S56 -> 8.9117887e+09
B83: Cashflow Statement
D84: Net Earnings | E84: [#'000] | O84: =O30 -> 1.7948511e+08 | P84: =P30 -> 5.2439696e+08 | Q84: =Q30 -> 1.3461849e+09 | R84: =R30 -> 2.6560979e+09 | S84: =S30 -> 5.1457366e+09
D85: Add: depreciation | E85: [#'000] | O85: =-O21 -> 9486784.3 | P85: =-P21 -> 10373799 | Q85: =-Q21 -> 11343749 | R85: =-R21 -> 12404389 | S85: =-S21 -> 13564200
D86: Changes in Working Capital | E86: [#'000]
D87: Inventory | E87: [#'000] | O87: =Cal!O104 -> -63765020 | P87: =Cal!P104 -> -2.1124999e+08 | Q87: =Cal!Q104 -> -3.103363e+08 | R87: =Cal!R104 -> -6.2786516e+08 | S87: =Cal!S104 -> -1.1929438e+09
D88: Trade Receivables | E88: [#'000] | O88: =Cal!O105 -> -1.177985e+08 | P88: =Cal!P105 -> -3.1655843e+08 | Q88: =Cal!Q105 -> -5.2232141e+08 | R88: =Cal!R105 -> -9.9241068e+08 | S88: =Cal!S105 -> -1.8855803e+09
D89: Trade Payables | E89: [#'000] | O89: =Cal!O106 -> 1.705761e+08 | P89: =Cal!P106 -> 2.6406249e+08 | Q89: =Cal!Q106 -> 3.8792037e+08 | R89: =Cal!R106 -> 7.8483145e+08 | S89: =Cal!S106 -> 1.4911798e+09
D91: Operating Cashflow | E91: [#'000] | O91: =SUM(O84:O90) -> 1.7798447e+08 | P91: =SUM(P84:P90) -> 2.7102482e+08 | Q91: =SUM(Q84:Q90) -> 9.1279127e+08 | R91: =SUM(R84:R90) -> 1.8330579e+09 | S91: =SUM(S84:S90) -> 3.5719565e+09
D93: Capex | E93: [#'000] | O93: =-Cal!O50 -> -42959023 | P93: =-Cal!P50 -> -46975692 | Q93: =-Cal!Q50 -> -51367919 | R93: =-Cal!R50 -> -56170820 | S93: =-Cal!S50 -> -61422791
D95: Investing CashFlow | E95: [#'000] | O95: =SUM(O93:O94) -> -42959023 | P95: =SUM(P93:P94) -> -46975692 | Q95: =SUM(Q93:Q94) -> -51367919 | R95: =SUM(R93:R94) -> -56170820 | S95: =SUM(S93:S94) -> -61422791
D97: Proceeds from borrowings | E97: [#'000] | O97: =Cal!O65 -> 577322462 | P97: =Cal!P65 -> 577322462 | Q97: =Cal!Q65 -> 577322462 | R97: =Cal!R65 -> 577322462 | S97: =Cal!S65 -> 577322462
D98: Repayment of borrowings | E98: [#'000] | O98: =Cal!O66 -> -219880819 | P98: =Cal!P66 -> -219880819 | Q98: =Cal!Q66 -> -219880819 | R98: =Cal!R66 -> -219880819 | S98: =Cal!S66 -> -219880819
D99: Dividend | E99: [#'000] | O99: =Cal!O75 -> -1.2563957e+08 | P99: =Cal!P75 -> -3.6707787e+08 | Q99: =Cal!Q75 -> -9.423294e+08 | R99: =Cal!R75 -> -1.8592685e+09 | S99: =Cal!S75 -> -3.6020157e+09
D101: Financing Cashflow | E101: [#'000] | O101: =SUM(O97:O100) -> 2.3180207e+08 | P101: =SUM(P97:P100) -> -9636228.3 | Q101: =SUM(Q97:Q100) -> -5.8488776e+08 | R101: =SUM(R97:R100) -> -1.5018269e+09 | S101: =SUM(S97:S100) -> -3.244574e+09
D103: Opening cash Balance | E103: [#'000] | O103: =N105 -> 100124789 | P103: =O105 -> 4.669523e+08 | Q103: =P105 -> 6.8136521e+08 | R103: =Q105 -> 9.579008e+08 | S103: =R105 -> 1.232961e+09
D104: Net Cashflow | E104: [#'000] | O104: =O91+O95+O101 -> 3.6682752e+08 | P104: =P91+P95+P101 -> 2.144129e+08 | Q104: =Q91+Q95+Q101 -> 2.7653559e+08 | R104: =R91+R95+R101 -> 2.7506018e+08 | S104: =S91+S95+S101 -> 2.659597e+08
D105: Closing Cash Balance | E105: [#'000] | N105: =FP!N22 -> 100124789 | O105: =SUM(O103:O104) -> 4.669523e+08 | P105: =SUM(P103:P104) -> 6.8136521e+08 | Q105: =SUM(Q103:Q104) -> 9.579008e+08 | R105: =SUM(R103:R104) -> 1.232961e+09 | S105: =SUM(S103:S104) -> 1.4989207e+09

Sheet Hist
A1: =Company -> BUA FOOD PLC
B3: Historicals
C5: Live Case : | I5: Start Date | L5: =K6+1 -> 44197 | M5: =L6+1 -> 44562 | N5: =M6+1 -> 44927 | O5: =N6+1 -> 45292 | P5: =O6+1 -> 45658 | Q5: =P6+1 -> 46023 | R5: =Q6+1 -> 46388 | S5: =R6+1 -> 46753
C6: Model Check : Ok | I6: End Date | K6: =EDATE(L6,-Month_in_period) -> 44196 | L6: =EDATE(M6,-Month_in_period) -> 44561 | M6: =EDATE(N6,-Month_in_period) -> 44926 | N6: =Historical_End_Date -> 45291 | O6: =EDATE(N6,Month_in_period) -> 45657 | P6: =EDATE(O6,Month_in_period) -> 46022 | Q6: =EDATE(P6,Month_in_period) -> 46387 | R6: =EDATE(Q6,Month_in_period) -> 46752 | S6: =EDATE(R6,Month_in_period) -> 47118
I7: Year | L7: =YEAR(L6) -> 2021 | M7: =YEAR(M6) -> 2022 | N7: =YEAR(N6) -> 2023 | P7: =YEAR(P6) -> 2025 | Q7: =YEAR(Q6) -> 2026 | R7: =YEAR(R6) -> 2027 | S7: =YEAR(S6) -> 2028
I8: Year Counter | L8: =M8-1 -> -2 | M8: =N8-1 -> -1 | N8: 0 | O8: =N8+1 -> 1 | P8: =O8+1 -> 2 | Q8: =P8+1 -> 3 | R8: =Q8+1 -> 4 | S8: =R8+1 -> 5
D9: Description | E9: Unit
B10: Income Statement
D12: Revenue from contracts with customers | L12: 333272234 | M12: 418347770 | N12: 729443355
D13: Cost of sales | L13: -230312612 | M13: -285555236 | N13: -468983756
D14: Gross profit | L14: =SUM(L12:L13) -> 102959622 | M14: =SUM(M12:M13) -> 132792534 | N14: =SUM(N12:N13) -> 260459599
D16: Administrative expenses | L16: -14626871 | M16: -18733919 | N16: -17212664
D17: Selling and distribution expenses | L17: -10135699 | M17: -14185483 | N17: -29849296
D18: Net impairment writeback on financial assets | L18: 143283 | M18: 2376501 | N18: -7890845
D19: Other income | L19: 1554540 | M19: 15242660 | N19: 809325
D21: Operating profit | L21: =SUM(L14:L20) -> 79894875 | M21: =SUM(M14:M20) -> 117492293 | N21: =SUM(N14:N20) -> 206316119
D23: Finance income | L23: 2892019 | M23: 39721 | N23: 2497371
D24: Finance cost | L24: -5047646 | M24: -8721781 | N24: -100678918
D25: Finance costs - net | L25: =SUM(L23:L24) -> -2155627 | M25: =SUM(M23:M24) -> -8682060 | N25: =SUM(N23:N24) -> -98181547
D27: Minimum tax charge | L27: -270527 | M27: -1580531 | N27: -10640
D29: Profit before income tax | L29: =L21+L25+L27 -> 77468721 | M29: =M21+M25+M27 -> 107229702 | N29: =N21+N25+N27 -> 108123932
D30: Income and deferred tax expense | L30: -7700636 | M30: -15885683 | N30: 3973565
D32: Profit after tax | L32: =L29+L30 -> 69768085 | M32: =M29+M30 -> 91344019 | N32: =N29+N30 -> 112097497
B34: Financial Position
C36: Assets
D37: Non-current assets
D38: Property, plant and equipment | L38: 321675653 | M38: 330523752 | N38: 357991862
D39: Right-of-use assets | L39: 1036460 | M39: 31165 | N39: 30324
D40: Biological assets | L40: 543901
D41: Investment in subsidiaries | L41: 0 | M41: 0 | N41: 0
D43: Total non-current assets | L43: =SUM(L38:L42) -> 323256014 | M43: =SUM(M38:M42) -> 330554917 | N43: =SUM(N38:N42) -> 358022186
D44: Current assets
D45: Inventories | L45: 24926471 | M45: 29760594 | N45: 112276641
D46: Trade receivables and other assets | L46: 52160076 | M46: 119325516 | N46: 151156115
D47: Cash and balances with banks | L47: 30338785 | M47: 32163428 | N47: 100124789
D48: Due from related parties | L48: 162788169 | M48: 95420170 | N48: 348860131
D49: Total current assets | L49: =SUM(L45:L48) -> 270213501 | M49: =SUM(M45:M48) -> 276669708 | N49: =SUM(N45:N48) -> 712417676
D51: Total assets | L51: =L43+L49 -> 593469515 | M51: =M43+M49 -> 607224625 | N51: =N43+N49 -> 1070439862
C53: Equity
D54: Equity
D55: Share capital | L55: 9000000 | M55: 9000000 | N55: 9000000
D56: Reorganisation reserves | L56: -943228 | M56: -943228 | N56: -943228
D57: Retained earnings | L57: 192661901 | M57: 222904565 | N57: 254002062
D58: Total equity | L58: =SUM(L55:L57) -> 200718673 | M58: =SUM(M55:M57) -> 230961337 | N58: =SUM(N55:N57) -> 262058834
C60: Liabilities
D61: Non-current liabilities
D62: Deferred tax liabilities | L62: 15225186 | M62: 33776943 | N62: 22306746
D63: Borrowings | L63: 4889870 | M63: 3475257 | N63: 1377286
D64: Lease liabilities | L64: 33611 | M64: 32678 | N64: 32650
D65: Government grants | L65: 0 | M65: 206665 | N65: 70211
D66: Deposit for shares | L66: 32243723 | M66: 32243723 | N66: 0
D67: Total non-current liabilities | L67: =SUM(L62:L66) -> 52392390 | M67: =SUM(M62:M66) -> 69735266 | N67: =SUM(N62:N66) -> 23786893
D69: Current liabilities
D70: Contract liabilites | L70: 40931459 | M70: 47139328 | N70: 68950583
D71: Current income tax payable | L71: 12778745 | M71: 8323257 | N71: 15819889
D72: Lease liabilities | L72: 4292441 | M72: 5073 | N72: 5073
D73: Bank overdraft | L73: 2851413 | M73: 4490873 | N73: 573175
D74: Borrowings | L74: 241159110 | M74: 208195755 | N74: 649699556
D75: Due to related parties | L75: 0 | M75: 0 | N75: 0
D76: Trade and other payables | L76: 38345284 | M76: 38325101 | N76: 49475977
D77: Government grants | L77: 0 | M77: 48635 | N77: 69882
D78: Total current liabilities | L78: =SUM(L70:L77) -> 340358452 | M78: =SUM(M70:M77) -> 306528022 | N78: =SUM(N70:N77) -> 784594135
D80: Total liabilities | L80: =L67+L78 -> 392750842 | M80: =M67+M78 -> 376263288 | N80: =N67+N78 -> 808381028
D82: Total equity and liabilities | L82: =L80+L58 -> 593469515 | M82: =M80+M58 -> 607224625 | N82: =N80+N58 -> 1070439862
B84: Reconstructed Financials
C85: Income Statement
D86: Revenue from contracts with customers | L86: =L115 -> 333272234 | M86: =M115 -> 418347770 | N86: =N115 -> 729443355
D87: Cost of sales | L87: =-L122 -> -224775825 | M87: =-M122 -> -280694270 | N87: =-N122 -> -462818283
D88: Gross profit | L88: =SUM(L86:L87) -> 108496409 | M88: =SUM(M86:M87) -> 137653500 | N88: =SUM(N86:N87) -> 266625072
D90: Administrative expenses | L90: =-L128 -> -11757023 | M90: =-M128 -> -15413481 | N90: =-N128 -> -13976642
D91: Selling and distribution expenses | L91: =-L133 -> -10135699 | M91: =-M133 -> -14185483 | N91: =-N133 -> -29849296
D92: Net impairment writeback on financial assets | L92: =L138 -> 143283 | M92: =M138 -> 2376501 | N92: =N138 -> -7890845
D93: Other income | L93: =L143 -> 1554540 | M93: =M143 -> 15242660 | N93: =N143 -> 809325
D94: EBITDA | L94: =SUM(L88:L93) -> 88301510 | M94: =SUM(M88:M93) -> 125673697 | N94: =SUM(N88:N93) -> 215717614
D96: Depreciation | L96: =L149 -> -8406635 | M96: =M149 -> -8181404 | N96: =N149 -> -9401495
D97: EBIT | L97: =SUM(L94:L96) -> 79894875 | M97: =SUM(M94:M96) -> 117492293 | N97: =SUM(N94:N96) -> 206316119
D99: Finance Income | L99: =L154 -> 2892019 | M99: =M154 -> 39721 | N99: =N154 -> 2497371
D100: Finance Cost | L100: =L159 -> -5047646 | M100: =M159 -> -8721781 | N100: =N159 -> -100678918
D101: EBT | L101: =SUM(L97:L100) -> 77739248 | M101: =SUM(M97:M100) -> 108810233 | N101: =SUM(N97:N100) -> 108134572
D103: Minimum tax | L103: =L164 -> -270527 | M103: =M164 -> -1580531 | N103: =N164 -> -10640
D104: Income and deferred tax expense | L104: =L169 -> -7700636 | M104: =M169 -> -15885683 | N104: =N169 -> 3973565
D105: Net Earnings | L105: =SUM(L101:L104) -> 69768085 | M105: =SUM(M101:M104) -> 91344019 | N105: =SUM(N101:N104) -> 112097497
D107: check | L107: =L105=L32 -> TRUE | M107: =M105=M32 -> TRUE | N107: =N105=N32 -> TRUE
B109: Reconstruct Note
C110: Income Statement
C112: Revenue
D113: Value per Audit | L113: =L12 -> 333272234 | M113: =M12 -> 418347770 | N113: =N12 -> 729443355
D115: Nothing Required | L115: =SUM(L113:L114) -> 333272234 | M115: =SUM(M113:M114) -> 418347770 | N115: =SUM(N113:N114) -> 729443355
C117: Cost of Sales
D118: Value per audit | L118: =-L13 -> 230312612 | M118: =-M13 -> 285555236 | N118: =-N13 -> 468983756
D119: Adjustment
D120: Depreciation of property, plant and equipment | L120: -4525882 | M120: -3855671 | N120: -6164631
D121: Depreciation of right-of-use assets | L121: -1010905 | M121: -1005295 | N121: -842
D122: Reconstruct Value | L122: =SUM(L118:L121) -> 224775825 | M122: =SUM(M118:M121) -> 280694270 | N122: =SUM(N118:N121) -> 462818283
C124: Administrative expenses
D125: Value per audit | L125: =-L16 -> 14626871 | M125: =-M16 -> 18733919 | N125: =-N16 -> 17212664
D126: Adjustment
D127: Depreciation of property, plant and equipment | L127: -2869848 | M127: -3320438 | N127: -3236022
D128: Reconstruct Value | L128: =SUM(L125:L127) -> 11757023 | M128: =SUM(M125:M127) -> 15413481 | N128: =SUM(N125:N127) -> 13976642
C130: Selling and distribution expenses
...

Sheet IS
A1: =Company -> BUA FOOD PLC
B3: Income Statement
C5: Live Case : | I5: Start Date | L5: =K6+1 -> 44197 | M5: =L6+1 -> 44562 | N5: =M6+1 -> 44927 | O5: =N6+1 -> 45292 | P5: =O6+1 -> 45658 | Q5: =P6+1 -> 46023 | R5: =Q6+1 -> 46388 | S5: =R6+1 -> 46753
C6: Model Check : Ok | I6: End Date | K6: =EDATE(L6,-Month_in_period) -> 44196 | L6: =EDATE(M6,-Month_in_period) -> 44561 | M6: =EDATE(N6,-Month_in_period) -> 44926 | N6: =Historical_End_Date -> 45291 | O6: =EDATE(N6,Month_in_period) -> 45657 | P6: =EDATE(O6,Month_in_period) -> 46022 | Q6: =EDATE(P6,Month_in_period) -> 46387 | R6: =EDATE(Q6,Month_in_period) -> 46752 | S6: =EDATE(R6,Month_in_period) -> 47118
I7: Year | L7: =YEAR(L6) -> 2021 | M7: =YEAR(M6) -> 2022 | N7: =YEAR(N6) -> 2023 | O7: =YEAR(O6) -> 2024 | P7: =YEAR(P6) -> 2025 | Q7: =YEAR(Q6) -> 2026 | R7: =YEAR(R6) -> 2027 | S7: =YEAR(S6) -> 2028
I8: Year Counter | L8: =M8-1 -> -2 | M8: =N8-1 -> -1 | N8: 0 | O8: =N8+1 -> 1 | P8: =O8+1 -> 2 | Q8: =P8+1 -> 3 | R8: =Q8+1 -> 4 | S8: =R8+1 -> 5
D9: Description | E9: Unit
B10: Income Statement
C11: Revenue from contracts with customers | E11: [#'000] | K11: 192860037 | L11: =Hist!L86 -> 333272234 | M11: =Hist!M86 -> 418347770 | N11: =Hist!N86 -> 729443355 | O11: =Cal!O17 -> 1.6047754e+09 | P11: =Cal!P17 -> 3.5305058e+09 | Q11: =Cal!Q17 -> 6.7079611e+09 | R11: =Cal!R17 -> 1.2745126e+10 | S11: =Cal!S17 -> 2.421574e+10
C12: Cost of sales | E12: [#'000] | L12: =Hist!L87 -> -224775825 | M12: =Hist!M87 -> -280694270 | N12: =Hist!N87 -> -462818283 | O12: =-Cal!O18 -> -1.235677e+09 | P12: =-Cal!P18 -> -2.7184895e+09 | Q12: =-Cal!Q18 -> -4.8968116e+09 | R12: =-Cal!R18 -> -9.303942e+09 | S12: =-Cal!S18 -> -1.767749e+10
C13: Gross profit | L13: =SUM(L11:L12) -> 108496409 | M13: =SUM(M11:M12) -> 137653500 | N13: =SUM(N11:N12) -> 266625072 | O13: =SUM(O11:O12) -> 3.6909834e+08 | P13: =SUM(P11:P12) -> 8.1201634e+08 | Q13: =SUM(Q11:Q12) -> 1.8111495e+09 | R13: =SUM(R11:R12) -> 3.441184e+09 | S13: =SUM(S11:S12) -> 6.5382497e+09
C15: Administrative expenses | E15: [#'000] | L15: =Hist!L90 -> -11757023 | M15: =Hist!M90 -> -15413481 | N15: =Hist!N90 -> -13976642 | O15: =-Cal!O32 -> -35305058 | P15: =-Cal!P32 -> -77671128 | Q15: =-Cal!Q32 -> -1.4757514e+08 | R15: =-Cal!R32 -> -2.8039277e+08 | S15: =-Cal!S32 -> -5.3274627e+08
C16: Selling and distribution expenses | E16: [#'000] | L16: =Hist!L91 -> -10135699 | M16: =Hist!M91 -> -14185483 | N16: =Hist!N91 -> -29849296 | O16: =-Cal!O33 -> -67400566 | P16: =-Cal!P33 -> -1.4828125e+08 | Q16: =-Cal!Q33 -> -2.8173437e+08 | R16: =-Cal!R33 -> -5.352953e+08 | S16: =-Cal!S33 -> -1.0170611e+09
C17: Net impairment writeback on financial assets | E17: [#'000] | L17: =Hist!L92 -> 143283 | M17: =Hist!M92 -> 2376501 | N17: =Hist!N92 -> -7890845 | O17: =Cal!O34 -> -7890845 | P17: =Cal!P34 -> -7890845 | Q17: =Cal!Q34 -> -7890845 | R17: =Cal!R34 -> -7890845 | S17: =Cal!S34 -> -7890845
C18: Other income | E18: [#'000] | L18: =Hist!L93 -> 1554540 | M18: =Hist!M93 -> 15242660 | N18: =Hist!N93 -> 809325 | O18: =Cal!O35 -> 40119385 | P18: =Cal!P35 -> 88262646 | Q18: =Cal!Q35 -> 1.6769903e+08 | R18: =Cal!R35 -> 3.1862815e+08 | S18: =Cal!S35 -> 6.0539349e+08
C19: EBITDA | E19: [#'000] | L19: =SUM(L13:L18) -> 88301510 | M19: =SUM(M13:M18) -> 125673697 | N19: =SUM(N13:N18) -> 215717614 | O19: =SUM(O13:O18) -> 2.9862125e+08 | P19: =SUM(P13:P18) -> 6.6643577e+08 | Q19: =SUM(Q13:Q18) -> 1.5416482e+09 | R19: =SUM(R13:R18) -> 2.9362333e+09 | S19: =SUM(S13:S18) -> 5.585945e+09
C21: Depreciation | E21: [#'000] | L21: =Hist!L96 -> -8406635 | M21: =Hist!M96 -> -8181404 | N21: =Hist!N96 -> -9401495 | O21: =Cal!O51 -> -9486784.3 | P21: =Cal!P51 -> -10373799 | Q21: =Cal!Q51 -> -11343749 | R21: =Cal!R51 -> -12404389 | S21: =Cal!S51 -> -13564200
C22: EBIT | E22: [#'000] | L22: =SUM(L19:L21) -> 79894875 | M22: =SUM(M19:M21) -> 117492293 | N22: =SUM(N19:N21) -> 206316119 | O22: =SUM(O19:O21) -> 2.8913447e+08 | P22: =SUM(P19:P21) -> 6.5606197e+08 | Q22: =SUM(Q19:Q21) -> 1.5303044e+09 | R22: =SUM(R19:R21) -> 2.9238289e+09 | S22: =SUM(S19:S21) -> 5.5723808e+09
C24: Finance Income | E24: [#'000] | L24: =Hist!L99 -> 2892019 | M24: =Hist!M99 -> 39721 | N24: =Hist!N99 -> 2497371 | O24: =Cal!O36 -> 2497371 | P24: =Cal!P36 -> 2497371 | Q24: =Cal!Q36 -> 2497371 | R24: =Cal!R36 -> 2497371 | S24: =Cal!S36 -> 2497371
C25: Finance Cost | E25: [#'000] | L25: =Hist!L100 -> -5047646 | M25: =Hist!M100 -> -8721781 | N25: =Hist!N100 -> -100678918 | O25: =Cal!O37 -> -100678918 | P25: =Cal!P37 -> -100678918 | Q25: =Cal!Q37 -> -100678918 | R25: =Cal!R37 -> -100678918 | S25: =Cal!S37 -> -100678918
C26: EBT | E26: [#'000] | L26: =SUM(L22:L25) -> 77739248 | M26: =SUM(M22:M25) -> 108810233 | N26: =SUM(N22:N25) -> 108134572 | O26: =SUM(O22:O25) -> 1.9095292e+08 | P26: =SUM(P22:P25) -> 5.5788042e+08 | Q26: =SUM(Q22:Q25) -> 1.4321229e+09 | R26: =SUM(R22:R25) -> 2.8256473e+09 | S26: =SUM(S22:S25) -> 5.4741992e+09
C28: Minimum tax | E28: [#'000] | L28: =Hist!L103 -> -270527 | M28: =Hist!M103 -> -1580531 | N28: =Hist!N103 -> -10640 | O28: =Cal!O38 -> -10640 | P28: =Cal!P38 -> -10640 | Q28: =Cal!Q38 -> -10640 | R28: =Cal!R38 -> -10640 | S28: =Cal!S38 -> -10640
C29: Income and deferred tax expense | E29: [#'000] | L29: =Hist!L104 -> -7700636 | M29: =Hist!M104 -> -15885683 | N29: =Hist!N104 -> 3973565 | O29: =-Cal!O41 -> -11457175 | P29: =-Cal!P41 -> -33472825 | Q29: =-Cal!Q41 -> -85927372 | R29: =-Cal!R41 -> -1.6953884e+08 | S29: =-Cal!S41 -> -3.2845195e+08
C30: Net Earnings | E30: [#'000] | L30: =SUM(L26:L29) -> 69768085 | M30: =SUM(M26:M29) -> 91344019 | N30: =SUM(N26:N29) -> 112097497 | O30: =SUM(O26:O29) -> 1.7948511e+08 | P30: =SUM(P26:P29) -> 5.2439696e+08 | Q30: =SUM(Q26:Q29) -> 1.3461849e+09 | R30: =SUM(R26:R29) -> 2.6560979e+09 | S30: =SUM(S26:S29) -> 5.1457366e+09

Sheet FP
A1: =Company -> BUA FOOD PLC
B3: Financial Position
C5: Live Case : | I5: Start Date | L5: =K6+1 -> 44197 | M5: =L6+1 -> 44562 | N5: =M6+1 -> 44927 | O5: =N6+1 -> 45292 | P5: =O6+1 -> 45658 | Q5: =P6+1 -> 46023 | R5: =Q6+1 -> 46388 | S5: =R6+1 -> 46753
C6: Model Check : Ok | I6: End Date | K6: =EDATE(L6,-Month_in_period) -> 44196 | L6: =EDATE(M6,-Month_in_period) -> 44561 | M6: =EDATE(N6,-Month_in_period) -> 44926 | N6: =Historical_End_Date -> 45291 | O6: =EDATE(N6,Month_in_period) -> 45657 | P6: =EDATE(O6,Month_in_period) -> 46022 | Q6: =EDATE(P6,Month_in_period) -> 46387 | R6: =EDATE(Q6,Month_in_period) -> 46752 | S6: =EDATE(R6,Month_in_period) -> 47118
I7: Year | L7: =YEAR(L6) -> 2021 | M7: =YEAR(M6) -> 2022 | N7: =YEAR(N6) -> 2023 | O7: =YEAR(O6) -> 2024 | P7: =YEAR(P6) -> 2025 | Q7: =YEAR(Q6) -> 2026 | R7: =YEAR(R6) -> 2027 | S7: =YEAR(S6) -> 2028
I8: Year Counter | L8: =M8-1 -> -2 | M8: =N8-1 -> -1 | N8: 0 | O8: =N8+1 -> 1 | P8: =O8+1 -> 2 | Q8: =P8+1 -> 3 | R8: =Q8+1 -> 4 | S8: =R8+1 -> 5
D9: Description | E9: Unit
B10: Financial Position
C12: Assets | L12: =IF(L26=L57,"OK","Not OK") -> OK | M12: =IF(M26=M57,"OK","Not OK") -> OK | N12: =IF(N26=N57,"OK","Not OK") -> OK | O12: =IF(O26=O57,"OK","Not OK") -> OK | P12: =IF(P26=P57,"OK","Not OK") -> OK | Q12: =IF(Q26=Q57,"OK","Not OK") -> OK | R12: =IF(R26=R57,"OK","Not OK") -> OK | S12: =IF(S26=S57,"OK","Not OK") -> OK
D13: Non-current assets
D14: Property, plant and equipment | E14: [#'000] | L14: =Hist!L38 -> 321675653 | M14: =Hist!M38 -> 330523752 | N14: =Hist!N38 -> 357991862 | O14: =Cal!O52 -> 3.914641e+08 | P14: =Cal!P52 -> 4.2806599e+08 | Q14: =Cal!Q52 -> 4.6809017e+08 | R14: =Cal!R52 -> 5.118566e+08 | S14: =Cal!S52 -> 5.5971519e+08
D15: Other Non- Current Assets | E15: [#'000] | L15: =Hist!L176 -> 1580361 | M15: =Hist!M176 -> 31165 | N15: =Hist!N176 -> 30324 | O15: =Cal!O55 -> 30324 | P15: =Cal!P55 -> 30324 | Q15: =Cal!Q55 -> 30324 | R15: =Cal!R55 -> 30324 | S15: =Cal!S55 -> 30324
D17: Total non-current assets | E17: [#'000] | L17: =SUM(L14:L16) -> 323256014 | M17: =SUM(M14:M16) -> 330554917 | N17: =SUM(N14:N16) -> 358022186 | O17: =SUM(O14:O16) -> 3.9149443e+08 | P17: =SUM(P14:P16) -> 4.2809632e+08 | Q17: =SUM(Q14:Q16) -> 4.6812049e+08 | R17: =SUM(R14:R16) -> 5.1188692e+08 | S17: =SUM(S14:S16) -> 5.5974551e+08
D18: Current assets
D19: Inventories | E19: [#'000] | L19: =Hist!L45 -> 24926471 | M19: 29760594 | N19: 112276641 | O19: =Cal!O92 -> 1.7604166e+08 | P19: =Cal!P92 -> 3.8729165e+08 | Q19: =Cal!Q92 -> 6.9762795e+08 | R19: =Cal!R92 -> 1.3254931e+09 | S19: =Cal!S92 -> 2.5184369e+09
D20: Trade receivables | E20: [#'000] | L20: =Hist!L182 -> 48967807 | M20: =Hist!M182 -> 107578798 | N20: =Hist!N182 -> 146000193 | O20: =Cal!O93 -> 2.6379869e+08 | P20: =Cal!P93 -> 5.8035712e+08 | Q20: =Cal!Q93 -> 1.1026785e+09 | R20: =Cal!R93 -> 2.0950892e+09 | S20: =Cal!S93 -> 3.9806695e+09
D21: Other assets | E21: [#'000] | L21: =Hist!L187 -> 3192269 | M21: =Hist!M187 -> 11746718 | N21: =Hist!N187 -> 5155922 | O21: =Cal!O109 -> 5155922 | P21: =Cal!P109 -> 5155922 | Q21: =Cal!Q109 -> 5155922 | R21: =Cal!R109 -> 5155922 | S21: =Cal!S109 -> 5155922
D22: Cash and balances with banks | E22: [#'000] | L22: =Hist!L47 -> 30338785 | M22: =Hist!M47 -> 32163428 | N22: =Hist!N47 -> 100124789 | O22: =CF!O32 -> 4.669523e+08 | P22: =CF!P32 -> 6.8136521e+08 | Q22: =CF!Q32 -> 9.579008e+08 | R22: =CF!R32 -> 1.232961e+09 | S22: =CF!S32 -> 1.4989207e+09
D23: Due from related parties | E23: [#'000] | L23: =Hist!L48 -> 162788169 | M23: =Hist!M48 -> 95420170 | N23: =Hist!N48 -> 348860131 | O23: =Cal!O110 -> 348860131 | P23: =Cal!P110 -> 348860131 | Q23: =Cal!Q110 -> 348860131 | R23: =Cal!R110 -> 348860131 | S23: =Cal!S110 -> 348860131
D24: Total current assets | E24: [#'000] | L24: =SUM(L19:L23) -> 270213501 | M24: =SUM(M19:M23) -> 276669708 | N24: =SUM(N19:N23) -> 712417676 | O24: =SUM(O19:O23) -> 1.2608087e+09 | P24: =SUM(P19:P23) -> 2.00303e+09 | Q24: =SUM(Q19:Q23) -> 3.1122233e+09 | R24: =SUM(R19:R23) -> 5.0075594e+09 | S24: =SUM(S19:S23) -> 8.3520432e+09
D26: Total assets | E26: [#'000] | L26: =L17+L24 -> 593469515 | M26: =M17+M24 -> 607224625 | N26: =N17+N24 -> 1070439862 | O26: =O17+O24 -> 1.6523031e+09 | P26: =P17+P24 -> 2.4311264e+09 | Q26: =Q17+Q24 -> 3.5803438e+09 | R26: =R17+R24 -> 5.5194463e+09 | S26: =S17+S24 -> 8.9117887e+09
C28: Equity
D29: Equity
D30: Share capital | E30: [#'000] | L30: =Hist!L55 -> 9000000 | M30: =Hist!M55 -> 9000000 | N30: =Hist!N55 -> 9000000 | O30: =Cal!O61 -> 9000000 | P30: =Cal!P61 -> 9000000 | Q30: =Cal!Q61 -> 9000000 | R30: =Cal!R61 -> 9000000 | S30: =Cal!S61 -> 9000000
D31: Reorganisation reserves | E31: [#'000] | L31: =Hist!L56 -> -943228 | M31: =Hist!M56 -> -943228 | N31: =Hist!N56 -> -943228 | O31: =Cal!O79 -> -943228 | P31: =Cal!P79 -> -943228 | Q31: =Cal!Q79 -> -943228 | R31: =Cal!R79 -> -943228 | S31: =Cal!S79 -> -943228
D32: Retained earnings | E32: [#'000] | L32: =Hist!L57 -> 192661901 | M32: =Hist!M57 -> 222904565 | N32: =Hist!N57 -> 254002062 | O32: =Cal!O76 -> 3.0784759e+08 | P32: =Cal!P76 -> 4.6516668e+08 | Q32: =Cal!Q76 -> 8.6902214e+08 | R32: =Cal!R76 -> 1.6658515e+09 | S32: =Cal!S76 -> 3.2095725e+09
D33: Total equity | E33: [#'000] | L33: =SUM(L30:L32) -> 200718673 | M33: =SUM(M30:M32) -> 230961337 | N33: =SUM(N30:N32) -> 262058834 | O33: =SUM(O30:O32) -> 3.1590437e+08 | P33: =SUM(P30:P32) -> 4.7322345e+08 | Q33: =SUM(Q30:Q32) -> 8.7707891e+08 | R33: =SUM(R30:R32) -> 1.6739083e+09 | S33: =SUM(S30:S32) -> 3.2176293e+09
D35: Liabilities
D36: Non-current liabilities
D37: Deferred tax liabilities | E37: [#'000] | L37: =Hist!L62 -> 15225186 | M37: =Hist!M62 -> 33776943 | N37: =Hist!N62 -> 22306746 | O37: =Cal!O113 -> 22306746 | P37: =Cal!P113 -> 22306746 | Q37: =Cal!Q113 -> 22306746 | R37: =Cal!R113 -> 22306746 | S37: =Cal!S113 -> 22306746
D38: Borrowings | E38: [#'000] | L38: =Hist!L63 -> 4889870 | M38: =Hist!M63 -> 3475257 | N38: =Hist!N63 -> 1377286 | O38: =Cal!O114 -> 1377286 | P38: =Cal!P114 -> 1377286 | Q38: =Cal!Q114 -> 1377286 | R38: =Cal!R114 -> 1377286 | S38: =Cal!S114 -> 1377286
D39: Lease liabilities | E39: [#'000] | L39: =Hist!L64 -> 33611 | M39: =Hist!M64 -> 32678 | N39: =Hist!N64 -> 32650 | O39: =Cal!O115 -> 32650 | P39: =Cal!P115 -> 32650 | Q39: =Cal!Q115 -> 32650 | R39: =Cal!R115 -> 32650 | S39: =Cal!S115 -> 32650
D40: Government grants | E40: [#'000] | L40: =Hist!L65 -> 0 | M40: =Hist!M65 -> 206665 | N40: =Hist!N65 -> 70211 | O40: =Cal!O116 -> 70211 | P40: =Cal!P116 -> 70211 | Q40: =Cal!Q116 -> 70211 | R40: =Cal!R116 -> 70211 | S40: =Cal!S116 -> 70211
D41: Deposit for shares | E41: [#'000] | L41: =Hist!L66 -> 32243723 | M41: =Hist!M66 -> 32243723 | N41: =Hist!N66 -> 0 | O41: =Cal!O117 -> 0 | P41: =Cal!P117 -> 0 | Q41: =Cal!Q117 -> 0 | R41: =Cal!R117 -> 0 | S41: =Cal!S117 -> 0
D42: Total non-current liabilities | E42: [#'000] | L42: =SUM(L37:L41) -> 52392390 | M42: =SUM(M37:M41) -> 69735266 | N42: =SUM(N37:N41) -> 23786893 | O42: =SUM(O37:O41) -> 23786893 | P42: =SUM(P37:P41) -> 23786893 | Q42: =SUM(Q37:Q41) -> 23786893 | R42: =SUM(R37:R41) -> 23786893 | S42: =SUM(S37:S41) -> 23786893
D44: Current liabilities
D45: Contract liabilites | E45: [#'000] | L45: =Hist!L70 -> 40931459 | M45: =Hist!M70 -> 47139328 | N45: =Hist!N70 -> 68950583 | O45: =Cal!O120 -> 68950583 | P45: =Cal!P120 -> 68950583 | Q45: =Cal!Q120 -> 68950583 | R45: =Cal!R120 -> 68950583 | S45: =Cal!S120 -> 68950583
D46: Current income tax payable | E46: [#'000] | L46: =Hist!L71 -> 12778745 | M46: =Hist!M71 -> 8323257 | N46: =Hist!N71 -> 15819889 | O46: =Cal!O121 -> 15819889 | P46: =Cal!P121 -> 15819889 | Q46: =Cal!Q121 -> 15819889 | R46: =Cal!R121 -> 15819889 | S46: =Cal!S121 -> 15819889
D47: Lease liabilities | E47: [#'000] | L47: =Hist!L72 -> 4292441 | M47: =Hist!M72 -> 5073 | N47: =Hist!N72 -> 5073 | O47: =Cal!O122 -> 5073 | P47: =Cal!P122 -> 5073 | Q47: =Cal!Q122 -> 5073 | R47: =Cal!R122 -> 5073 | S47: =Cal!S122 -> 5073
D48: Bank overdraft | E48: [#'000] | L48: =Hist!L73 -> 2851413 | M48: =Hist!M73 -> 4490873 | N48: =Hist!N73 -> 573175 | O48: =Cal!O123 -> 573175 | P48: =Cal!P123 -> 573175 | Q48: =Cal!Q123 -> 573175 | R48: =Cal!R123 -> 573175 | S48: =Cal!S123 -> 573175
D49: Borrowings | E49: [#'000] | L49: =Hist!L74 -> 241159110 | M49: =Hist!M74 -> 208195755 | N49: =Hist!N74 -> 649699556 | O49: =Cal!O67 -> 1007141199 | P49: =Cal!P67 -> 1364582842 | Q49: =Cal!Q67 -> 1722024485 | R49: =Cal!R67 -> 2079466128 | S49: =Cal!S67 -> 2436907771
D50: Due to related parties | E50: [#'000] | L50: =Hist!L75 -> 0 | M50: =Hist!M75 -> 0 | N50: =Hist!N75 -> 0 | O50: =Cal!O124 -> 0 | P50: =Cal!P124 -> 0 | Q50: =Cal!Q124 -> 0 | R50: =Cal!R124 -> 0 | S50: =Cal!S124 -> 0
D51: Trade and other payables | E51: [#'000] | L51: =Hist!L76 -> 38345284 | M51: =Hist!M76 -> 38325101 | N51: =Hist!N76 -> 49475977 | O51: =Cal!O94 -> 2.2005208e+08 | P51: =Cal!P94 -> 4.8411457e+08 | Q51: =Cal!Q94 -> 8.7203494e+08 | R51: =Cal!R94 -> 1.6568664e+09 | S51: =Cal!S94 -> 3.1480461e+09
D52: Government grants | E52: [#'000] | L52: =Hist!L77 -> 0 | M52: =Hist!M77 -> 48635 | N52: =Hist!N77 -> 69882 | O52: {=Cal!O125} -> 69882 | P52: {=Cal!P125} -> 69882 | Q52: {=Cal!Q125} -> 69882 | R52: {=Cal!R125} -> 69882 | S52: {=Cal!S125} -> 69882
D53: Total current liabilities | E53: [#'000] | L53: =SUM(L45:L52) -> 340358452 | M53: =SUM(M45:M52) -> 306528022 | N53: =SUM(N45:N52) -> 784594135 | O53: =SUM(O45:O52) -> 1.3126119e+09 | P53: =SUM(P45:P52) -> 1.934116e+09 | Q53: =SUM(Q45:Q52) -> 2.679478e+09 | R53: =SUM(R45:R52) -> 3.8217511e+09 | S53: =SUM(S45:S52) -> 5.6703725e+09
D55: Total liabilities | E55: [#'000] | L55: =L42+L53 -> 392750842 | M55: =M42+M53 -> 376263288 | N55: =N42+N53 -> 808381028 | O55: =O42+O53 -> 1.3363988e+09 | P55: =P42+P53 -> 1.9579029e+09 | Q55: =Q42+Q53 -> 2.7032649e+09 | R55: =R42+R53 -> 3.845538e+09 | S55: =S42+S53 -> 5.6941594e+09
D57: Total equity and liabilities | E57: [#'000] | L57: =L55+L33 -> 593469515 | M57: =M55+M33 -> 607224625 | N57: =N55+N33 -> 1070439862 | O57: =O55+O33 -> 1.6523031e+09 | P57: =P55+P33 -> 2.4311264e+09 | Q57: =Q55+Q33 -> 3.5803438e+09 | R57: =R55+R33 -> 5.5194463e+09 | S57: =S55+S33 -> 8.9117887e+09

Sheet CF
A1: =Company -> BUA FOOD PLC
B3: Cashflow Statement
C5: Live Case : | I5: Start Date | L5: =K6+1 -> 44197 | M5: =L6+1 -> 44562 | N5: =M6+1 -> 44927 | O5: =N6+1 -> 45292 | P5: =O6+1 -> 45658 | Q5: =P6+1 -> 46023 | R5: =Q6+1 -> 46388 | S5: =R6+1 -> 46753
C6: Model Check : Ok | I6: End Date | K6: =EDATE(L6,-Month_in_period) -> 44196 | L6: =EDATE(M6,-Month_in_period) -> 44561 | M6: =EDATE(N6,-Month_in_period) -> 44926 | N6: =Historical_End_Date -> 45291 | O6: =EDATE(N6,Month_in_period) -> 45657 | P6: =EDATE(O6,Month_in_period) -> 46022 | Q6: =EDATE(P6,Month_in_period) -> 46387 | R6: =EDATE(Q6,Month_in_period) -> 46752 | S6: =EDATE(R6,Month_in_period) -> 47118
I7: Year | L7: =YEAR(L6) -> 2021 | M7: =YEAR(M6) -> 2022 | N7: =YEAR(N6) -> 2023 | O7: =YEAR(O6) -> 2024 | P7: =YEAR(P6) -> 2025 | Q7: =YEAR(Q6) -> 2026 | R7: =YEAR(R6) -> 2027 | S7: =YEAR(S6) -> 2028
I8: Year Counter | L8: =M8-1 -> -2 | M8: =N8-1 -> -1 | N8: 0 | O8: =N8+1 -> 1 | P8: =O8+1 -> 2 | Q8: =P8+1 -> 3 | R8: =Q8+1 -> 4 | S8: =R8+1 -> 5
D9: Description | E9: Unit
B10: Cashflow Statement
D11: Net Earnings | E11: [#'000] | O11: =IS!O30 -> 1.7948511e+08 | P11: =IS!P30 -> 5.2439696e+08 | Q11: =IS!Q30 -> 1.3461849e+09 | R11: =IS!R30 -> 2.6560979e+09 | S11: =IS!S30 -> 5.1457366e+09
D12: Add: depreciation | E12: [#'000] | O12: =-IS!O21 -> 9486784.3 | P12: =-IS!P21 -> 10373799 | Q12: =-IS!Q21 -> 11343749 | R12: =-IS!R21 -> 12404389 | S12: =-IS!S21 -> 13564200
D13: Changes in Working Capital | E13: [#'000]
D14: Inventory | E14: [#'000] | O14: =Cal!O104 -> -63765020 | P14: =Cal!P104 -> -2.1124999e+08 | Q14: =Cal!Q104 -> -3.103363e+08 | R14: =Cal!R104 -> -6.2786516e+08 | S14: =Cal!S104 -> -1.1929438e+09
D15: Trade Receivables | E15: [#'000] | O15: =Cal!O105 -> -1.177985e+08 | P15: =Cal!P105 -> -3.1655843e+08 | Q15: =Cal!Q105 -> -5.2232141e+08 | R15: =Cal!R105 -> -9.9241068e+08 | S15: =Cal!S105 -> -1.8855803e+09
D16: Trade Payables | E16: [#'000] | O16: =Cal!O106 -> 1.705761e+08 | P16: =Cal!P106 -> 2.6406249e+08 | Q16: =Cal!Q106 -> 3.8792037e+08 | R16: =Cal!R106 -> 7.8483145e+08 | S16: =Cal!S106 -> 1.4911798e+09
D18: Operating Cashflow | E18: [#'000] | O18: =SUM(O11:O17) -> 1.7798447e+08 | P18: =SUM(P11:P17) -> 2.7102482e+08 | Q18: =SUM(Q11:Q17) -> 9.1279127e+08 | R18: =SUM(R11:R17) -> 1.8330579e+09 | S18: =SUM(S11:S17) -> 3.5719565e+09
D20: Capex | E20: [#'000] | O20: =-Cal!O50 -> -42959023 | P20: =-Cal!P50 -> -46975692 | Q20: =-Cal!Q50 -> -51367919 | R20: =-Cal!R50 -> -56170820 | S20: =-Cal!S50 -> -61422791
D22: Investing CashFlow | E22: [#'000] | O22: =SUM(O20:O21) -> -42959023 | P22: =SUM(P20:P21) -> -46975692 | Q22: =SUM(Q20:Q21) -> -51367919 | R22: =SUM(R20:R21) -> -56170820 | S22: =SUM(S20:S21) -> -61422791
D24: Proceeds from borrowings | E24: [#'000] | O24: =Cal!O65 -> 577322462 | P24: =Cal!P65 -> 577322462 | Q24: =Cal!Q65 -> 577322462 | R24: =Cal!R65 -> 577322462 | S24: =Cal!S65 -> 577322462
D25: Repayment of borrowings | E25: [#'000] | O25: =Cal!O66 -> -219880819 | P25: =Cal!P66 -> -219880819 | Q25: =Cal!Q66 -> -219880819 | R25: =Cal!R66 -> -219880819 | S25: =Cal!S66 -> -219880819
D26: Dividend | E26: [#'000] | O26: =Cal!O75 -> -1.2563957e+08 | P26: =Cal!P75 -> -3.6707787e+08 | Q26: =Cal!Q75 -> -9.423294e+08 | R26: =Cal!R75 -> -1.8592685e+09 | S26: =Cal!S75 -> -3.6020157e+09
D28: Financing Cashflow | E28: [#'000] | O28: =SUM(O24:O27) -> 2.3180207e+08 | P28: =SUM(P24:P27) -> -9636228.3 | Q28: =SUM(Q24:Q27) -> -5.8488776e+08 | R28: =SUM(R24:R27) -> -1.5018269e+09 | S28: =SUM(S24:S27) -> -3.244574e+09
D30: Opening cash Balance | E30: [#'000] | O30: =N32 -> 100124789 | P30: =O32 -> 4.669523e+08 | Q30: =P32 -> 6.8136521e+08 | R30: =Q32 -> 9.579008e+08 | S30: =R32 -> 1.232961e+09
D31: Net Cashflow | E31: [#'000] | O31: =O18+O22+O28 -> 3.6682752e+08 | P31: =P18+P22+P28 -> 2.144129e+08 | Q31: =Q18+Q22+Q28 -> 2.7653559e+08 | R31: =R18+R22+R28 -> 2.7506018e+08 | S31: =S18+S22+S28 -> 2.659597e+08
D32: Closing Cash Balance | E32: [#'000] | N32: =FP!N22 -> 100124789 | O32: =SUM(O30:O31) -> 4.669523e+08 | P32: =SUM(P30:P31) -> 6.8136521e+08 | Q32: =SUM(Q30:Q31) -> 9.579008e+08 | R32: =SUM(R30:R31) -> 1.232961e+09 | S32: =SUM(S30:S31) -> 1.4989207e+09

Sheet DCF
A1: =Company -> BUA FOOD PLC
B3: Template
C5: Live Case : | I5: Start Date | L5: =K6+1 -> 44197 | M5: =L6+1 -> 44562 | N5: =M6+1 -> 44927 | O5: =N6+1 -> 45292 | P5: =O6+1 -> 45658 | Q5: =P6+1 -> 46023 | R5: =Q6+1 -> 46388 | S5: =R6+1 -> 46753
C6: Model Check : Ok | I6: End Date | K6: =EDATE(L6,-Month_in_period) -> 44196 | L6: =EDATE(M6,-Month_in_period) -> 44561 | M6: =EDATE(N6,-Month_in_period) -> 44926 | N6: =Historical_End_Date -> 45291 | O6: =EDATE(N6,Month_in_period) -> 45657 | P6: =EDATE(O6,Month_in_period) -> 46022 | Q6: =EDATE(P6,Month_in_period) -> 46387 | R6: =EDATE(Q6,Month_in_period) -> 46752 | S6: =EDATE(R6,Month_in_period) -> 47118
I7: Year | L7: =YEAR(L6) -> 2021 | M7: =YEAR(M6) -> 2022 | N7: =YEAR(N6) -> 2023 | O7: =YEAR(O6) -> 2024 | P7: =YEAR(P6) -> 2025 | Q7: =YEAR(Q6) -> 2026 | R7: =YEAR(R6) -> 2027 | S7: =YEAR(S6) -> 2028
I8: Year Counter | L8: =M8-1 -> -2 | M8: =N8-1 -> -1 | N8: 0 | O8: =N8+1 -> 1 | P8: =O8+1 -> 2 | Q8: =P8+1 -> 3 | R8: =Q8+1 -> 4 | S8: =R8+1 -> 5
D9: Description | E9: Unit
B10: Cost of Capital
C11: Cost of Equity
D12: Risk free rate | E12: [%] | N12: =Inp!I11 -> 0.20738
D13: Beta | N13: =Inp!I12 -> 0.27439
D14: Equity Risk premium | E14: [%] | N14: =Inp!I13 -> 0.1571
D15: Cost of Equity | E15: [%] | N15: =N12+(N13*N14) -> 0.25048667
C17: Cost of Debt
D18: Cost of debt pre-tax | E18: [%] | N18: =Inp!I14 -> 0.19
D19: Tax rate | E19: [%] | N19: =Inp!I20 -> 0.06
D20: Post tax Cost of Debt | E20: [%] | N20: =N18*(1-N19) -> 0.1786
C22: Weight of Equity and Debt
D23: Equity | M23: =N23/$N$25 -> 0.91610999 | N23: =Inp!I18 -> 7110000000
D24: Debt | M24: =N24/$N$25 -> 0.083890014 | N24: =Inp!I19 -> 651076842
D25: Total | N25: =SUM(N23:N24) -> 7761076842
C27: WACC
D28: Cost of Equity | E28: [%] | N28: =N15 -> 0.25048667
D29: Cost of Debt | E29: [%] | N29: =N20 -> 0.1786
D30: Weight of Equity | E30: [%] | N30: =M23 -> 0.91610999
D31: Weight of Debt | E31: [%] | N31: =M24 -> 0.083890014
D32: WACC | E32: [%] | N32: =SUMPRODUCT(N28:N29,N30:N31) -> 0.2444561
D34: Valuation Date | N34: =DATE(O7,11,14) -> 45610
B36: Unlevered Free Cash Flow
D37: EBIT | E37: [#'000] | O37: =IS!O22 -> 2.8913447e+08 | P37: =IS!P22 -> 6.5606197e+08 | Q37: =IS!Q22 -> 1.5303044e+09 | R37: =IS!R22 -> 2.9238289e+09 | S37: =IS!S22 -> 5.5723808e+09
D38: Taxes | E38: [#'000] | O38: =-O37*$N$19 -> -17348068 | P38: =-P37*$N$19 -> -39363718 | Q38: =-Q37*$N$19 -> -91818265 | R38: =-R37*$N$19 -> -1.7542973e+08 | S38: =-S37*$N$19 -> -3.3434285e+08
D39: Add: Depreciation | E39: [#'000] | O39: =-IS!O21 -> 9486784.3 | P39: =-IS!P21 -> 10373799 | Q39: =-IS!Q21 -> 11343749 | R39: =-IS!R21 -> 12404389 | S39: =-IS!S21 -> 13564200
D40: Changes in Working Capital | E40: [#'000] | O40: =Cal!O101 -> -10987421 | P40: =Cal!P101 -> -2.6374593e+08 | Q40: =Cal!Q101 -> -4.4473734e+08 | R40: =Cal!R101 -> -8.3544439e+08 | S40: =Cal!S101 -> -1.5873443e+09
D41: Capex | E41: [#'000] | O41: =-Cal!O50 -> -42959023 | P41: =-Cal!P50 -> -46975692 | Q41: =-Cal!Q50 -> -51367919 | R41: =-Cal!R50 -> -56170820 | S41: =-Cal!S50 -> -61422791
E42: [#'000] | O42: =SUM(O37:O41) -> 2.2732674e+08 | P42: =SUM(P37:P41) -> 3.1635043e+08 | Q42: =SUM(Q37:Q41) -> 9.5372465e+08 | R42: =SUM(R37:R41) -> 1.8691883e+09 | S42: =SUM(S37:S41) -> 3.602835e+09
D43: Cash flow Adjustment | E43: [%] | O43: =O45-N45 -> 0.13055556 | P43: =P45-O45 -> 1 | Q43: =Q45-P45 -> 1 | R43: =R45-Q45 -> 1 | S43: =S45-R45 -> 1
D44: UFCF | E44: [#'000] | O44: =O42*O43 -> 29678769 | P44: =P42*P43 -> 3.1635043e+08 | Q44: =Q42*Q43 -> 9.5372465e+08 | R44: =R42*R43 -> 1.8691883e+09 | S44: =S42*S43 -> 3.602835e+09
D45: Mid-period Adjustment | O45: =YEARFRAC($N$34,O6) -> 0.13055556 | P45: =YEARFRAC($N$34,P6) -> 1.1305556 | Q45: =YEARFRAC($N$34,Q6) -> 2.1305556 | R45: =YEARFRAC($N$34,R6) -> 3.1305556 | S45: =YEARFRAC($N$34,S6) -> 4.1305556
D46: Discount Factor | O46: =(1+$N$32)^O45 -> 1.0289638 | P46: =(1+$N$32)^P45 -> 1.2805003 | Q46: =(1+$N$32)^Q45 -> 1.5935264 | R46: =(1+$N$32)^R45 -> 1.9830737 | S46: =(1+$N$32)^S45 -> 2.4678481
D48: Present Value of UFCF | E48: [#'000] | O48: =O44/O46 -> 28843355 | P48: =P44/P46 -> 2.470522e+08 | Q48: =Q44/Q46 -> 5.9849942e+08 | R48: =R44/R46 -> 9.425713e+08 | S48: =S44/S46 -> 1.4599095e+09
D50: Terminal Value
D51: Terminal Growth rate | E51: [%] | I51: =Inp!I17 -> 0.07
D52: WACC | E52: [%] | I52: =N32 -> 0.2444561
D53: Terminal Value | E53: [#'000] | I53: =S44*(1+I51)/(I52-I51) -> 2.2097442e+10
D54: PV of Terminal Value | E54: [#'000] | I54: =I53/S46 -> 8.9541337e+09
D56: Enterprise Value
D57: Present Value of UFCF | I57: =SUM(O48:S48) -> 3.2768758e+09
D58: Present Value of Terminal Value | I58: =I54 -> 8.9541337e+09
D59: Enterprise Value | E59: [#'000] | I59: =SUM(I57:I58) -> 1.223101e+10
D61: Equity Value
D62: Enterprise Value | I62: =I59 -> 1.223101e+10
D63: Add: Cash | I63: =FP!N22 -> 100124789
D64: Less: Debt | I64: =-Inp!I19 -> -651076842 | L64: =D59 -> Enterprise Value | M64: =I59 -> 1.223101e+10
D65: Equity Value | E65: [#'000] | I65: =SUM(I62:I64) -> 1.1680057e+10 | L65: =D65 -> Equity Value | M65: =I65 -> 1.1680057e+10
D67: Share Outstanding | E67: [#'000] | I67: =Inp!I16 -> 18000000
D68: Target Price /Implied Price | I68: =I65/I67 -> 648.89208
D69: Current Share Price | I69: =Inp!I15 -> 394.9
D70: Upside /Downside | I70: =I68/I69-1 -> 0.64318076
D71: Recommendation | I71: Buy Share Now

Sheet Cal
A1: =Company -> BUA FOOD PLC
B3: Calculations
C5: Live Case : | I5: Start Date | L5: =K6+1 -> 44197 | M5: =L6+1 -> 44562 | N5: =M6+1 -> 44927 | O5: =N6+1 -> 45292 | P5: =O6+1 -> 45658 | Q5: =P6+1 -> 46023 | R5: =Q6+1 -> 46388 | S5: =R6+1 -> 46753
C6: Model Check : Ok | I6: End Date | K6: =EDATE(L6,-Month_in_period) -> 44196 | L6: =EDATE(M6,-Month_in_period) -> 44561 | M6: =EDATE(N6,-Month_in_period) -> 44926 | N6: =Historical_End_Date -> 45291 | O6: =EDATE(N6,Month_in_period) -> 45657 | P6: =EDATE(O6,Month_in_period) -> 46022 | Q6: =EDATE(P6,Month_in_period) -> 46387 | R6: =EDATE(Q6,Month_in_period) -> 46752 | S6: =EDATE(R6,Month_in_period) -> 47118
I7: Year | L7: =YEAR(L6) -> 2021 | M7: =YEAR(M6) -> 2022 | N7: =YEAR(N6) -> 2023 | O7: =YEAR(O6) -> 2024 | P7: =YEAR(P6) -> 2025 | Q7: =YEAR(Q6) -> 2026 | R7: =YEAR(R6) -> 2027 | S7: =YEAR(S6) -> 2028
I8: Year Counter | L8: =M8-1 -> -2 | M8: =N8-1 -> -1 | N8: 0 | O8: =N8+1 -> 1 | P8: =O8+1 -> 2 | Q8: =P8+1 -> 3 | R8: =Q8+1 -> 4 | S8: =R8+1 -> 5
D9: Description | E9: Unit
B10: Income Statement
C11: Above the line
D12: Drivers
D13: Revenue | E13: [year on year Growth] | O13: =Inp!O24 -> 1.2 | P13: =Inp!P24 -> 1.2 | Q13: =Inp!Q24 -> 0.9 | R13: =Inp!R24 -> 0.9 | S13: =Inp!S24 -> 0.9
D14: Cost of Sales | E14: [% of Revenue] | O14: =Inp!O25 -> 0.77 | P14: =Inp!P25 -> 0.77 | Q14: =Inp!Q25 -> 0.73 | R14: =Inp!R25 -> 0.73 | S14: =Inp!S25 -> 0.73
D16: Calculation
D17: Revenue | E17: [#'000] | N17: =IS!N11 -> 729443355 | O17: =N17*(1+O13) -> 1.6047754e+09 | P17: =O17*(1+P13) -> 3.5305058e+09 | Q17: =P17*(1+Q13) -> 6.7079611e+09 | R17: =Q17*(1+R13) -> 1.2745126e+10 | S17: =R17*(1+S13) -> 2.421574e+10
D18: Cost of Sales | E18: [#'000] | O18: =O17*O14 -> 1.235677e+09 | P18: =P17*P14 -> 2.7184895e+09 | Q18: =Q17*Q14 -> 4.8968116e+09 | R18: =R17*R14 -> 9.303942e+09 | S18: =S17*S14 -> 1.767749e+10
C20: Below the line
D21: Administrative expenses | E21: [% of Revenue] | O21: =Inp!O28 -> 0.022 | P21: =Inp!P28 -> 0.022 | Q21: =Inp!Q28 -> 0.022 | R21: =Inp!R28 -> 0.022 | S21: =Inp!S28 -> 0.022
D22: Selling and distribution expenses | E22: [% of Revenue] | O22: =Inp!O29 -> 0.042 | P22: =Inp!P29 -> 0.042 | Q22: =Inp!Q29 -> 0.042 | R22: =Inp!R29 -> 0.042 | S22: =Inp!S29 -> 0.042
D23: Net impairment writeback on financial assets | E23: [Ending Balance] | O23: =Inp!O30 -> -7890845 | P23: =Inp!P30 -> -7890845 | Q23: =Inp!Q30 -> -7890845 | R23: =Inp!R30 -> -7890845 | S23: =Inp!S30 -> -7890845
D24: Other income | E24: [% of Revenue] | O24: =Inp!O31 -> 0.025 | P24: =Inp!P31 -> 0.025 | Q24: =Inp!Q31 -> 0.025 | R24: =Inp!R31 -> 0.025 | S24: =Inp!S31 -> 0.025
D25: Depreciation | E25: [% of PPE] | O25: =Inp!O32 -> 0.0265 | P25: =Inp!P32 -> 0.0265 | Q25: =Inp!Q32 -> 0.0265 | R25: =Inp!R32 -> 0.0265 | S25: =Inp!S32 -> 0.0265
D26: Finance Income | E26: [Ending Balance] | O26: =Inp!O33 -> 2497371 | P26: =Inp!P33 -> 2497371 | Q26: =Inp!Q33 -> 2497371 | R26: =Inp!R33 -> 2497371 | S26: =Inp!S33 -> 2497371
D27: Finance Cost | E27: [Ending Balance] | O27: =Inp!O34 -> -100678918 | P27: =Inp!P34 -> -100678918 | Q27: =Inp!Q34 -> -100678918 | R27: =Inp!R34 -> -100678918 | S27: =Inp!S34 -> -100678918
D28: Minimum tax | E28: [Ending Balance] | O28: =Inp!O35 -> -10640 | P28: =Inp!P35 -> -10640 | Q28: =Inp!Q35 -> -10640 | R28: =Inp!R35 -> -10640 | S28: =Inp!S35 -> -10640
D29: Income and deferred tax expense | E29: [% of EBT] | O29: =Inp!O36 -> 0.06 | P29: =Inp!P36 -> 0.06 | Q29: =Inp!Q36 -> 0.06 | R29: =Inp!R36 -> 0.06 | S29: =Inp!S36 -> 0.06
D31: Calculation
D32: Administrative expenses | E32: [#'000] | O32: =O21*O17 -> 35305058 | P32: =P21*P17 -> 77671128 | Q32: =Q21*Q17 -> 1.4757514e+08 | R32: =R21*R17 -> 2.8039277e+08 | S32: =S21*S17 -> 5.3274627e+08
D33: Selling and distribution expenses | E33: [#'000] | O33: =O22*O17 -> 67400566 | P33: =P22*P17 -> 1.4828125e+08 | Q33: =Q22*Q17 -> 2.8173437e+08 | R33: =R22*R17 -> 5.352953e+08 | S33: =S22*S17 -> 1.0170611e+09
D34: Net impairment writeback on financial assets | E34: [#'000] | O34: =O23 -> -7890845 | P34: =P23 -> -7890845 | Q34: =Q23 -> -7890845 | R34: =R23 -> -7890845 | S34: =S23 -> -7890845
D35: Other income | E35: [#'000] | O35: =O24*O17 -> 40119385 | P35: =P24*P17 -> 88262646 | Q35: =Q24*Q17 -> 1.6769903e+08 | R35: =R24*R17 -> 3.1862815e+08 | S35: =S24*S17 -> 6.0539349e+08
D36: Finance Income | E36: [#'000] | O36: =O26 -> 2497371 | P36: =P26 -> 2497371 | Q36: =Q26 -> 2497371 | R36: =R26 -> 2497371 | S36: =S26 -> 2497371
D37: Finance Cost | E37: [#'000] | O37: =O27 -> -100678918 | P37: =P27 -> -100678918 | Q37: =Q27 -> -100678918 | R37: =R27 -> -100678918 | S37: =S27 -> -100678918
D38: Minimum tax | E38: [#'000] | O38: =O28 -> -10640 | P38: =P28 -> -10640 | Q38: =Q28 -> -10640 | R38: =R28 -> -10640 | S38: =S28 -> -10640
D40: EBT | E40: [#'000] | O40: =IS!O26 -> 1.9095292e+08 | P40: =IS!P26 -> 5.5788042e+08 | Q40: =IS!Q26 -> 1.4321229e+09 | R40: =IS!R26 -> 2.8256473e+09 | S40: =IS!S26 -> 5.4741992e+09
D41: Income and deferred tax expense | E41: [#'000] | O41: =O29*O40 -> 11457175 | P41: =P29*P40 -> 33472825 | Q41: =Q29*Q40 -> 85927372 | R41: =R29*R40 -> 1.6953884e+08 | S41: =S29*S40 -> 3.2845195e+08
B43: Financial Position
C44: PPE Schedule
D45: Drivers
D46: Depreciation | O46: =Inp!O32 -> 0.0265 | P46: =Inp!P32 -> 0.0265 | Q46: =Inp!Q32 -> 0.0265 | R46: =Inp!R32 -> 0.0265 | S46: =Inp!S32 -> 0.0265
D47: Incremental Capex | O47: =Inp!O44 -> 0.12 | P47: =Inp!P44 -> 0.12 | Q47: =Inp!Q44 -> 0.12 | R47: =Inp!R44 -> 0.12 | S47: =Inp!S44 -> 0.12
D49: Opening Balance | E49: [#'000] | O49: =N52 -> 357991862 | P49: =O52 -> 3.914641e+08 | Q49: =P52 -> 4.2806599e+08 | R49: =Q52 -> 4.6809017e+08 | S49: =R52 -> 5.118566e+08
D50: Capex | E50: [#'000] | O50: =O49*O47 -> 42959023 | P50: =P49*P47 -> 46975692 | Q50: =Q49*Q47 -> 51367919 | R50: =R49*R47 -> 56170820 | S50: =S49*S47 -> 61422791
D51: Depreciation | E51: [#'000] | O51: =-O46*O49 -> -9486784.3 | P51: =-P46*P49 -> -10373799 | Q51: =-Q46*Q49 -> -11343749 | R51: =-R46*R49 -> -12404389 | S51: =-S46*S49 -> -13564200
D52: Closing Balance | E52: [#'000] | N52: =FP!N14 -> 357991862 | O52: =SUM(O49:O51) -> 3.914641e+08 | P52: =SUM(P49:P51) -> 4.2806599e+08 | Q52: =SUM(Q49:Q51) -> 4.6809017e+08 | R52: =SUM(R49:R51) -> 5.118566e+08 | S52: =SUM(S49:S51) -> 5.5971519e+08
C54: Other Non- Current Assets
D55: Other Non-Current Asset | E55: [#'000] | O55: =Inp!O50 -> 30324 | P55: =Inp!P50 -> 30324 | Q55: =Inp!Q50 -> 30324 | R55: =Inp!R50 -> 30324 | S55: =Inp!S50 -> 30324
C57: Shareholder Equity Schedule
D58: Opening Balance | E58: [#'000] | O58: =N61 -> 9000000 | P58: =O61 -> 9000000 | Q58: =P61 -> 9000000 | R58: =Q61 -> 9000000 | S58: =R61 -> 9000000
D59: Share issues | E59: [#'000] | O59: 0 | P59: 0 | Q59: 0 | R59: 0 | S59: 0
D60: Share Buy Back | E60: [#'000] | O60: 0 | P60: 0 | Q60: 0 | R60: 0 | S60: 0
D61: Closing Balance | E61: [#'000] | N61: =FP!N30 -> 9000000 | O61: =SUM(O58:O60) -> 9000000 | P61: =SUM(P58:P60) -> 9000000 | Q61: =SUM(Q58:Q60) -> 9000000 | R61: =SUM(R58:R60) -> 9000000 | S61: =SUM(S58:S60) -> 9000000
C63: Debt Schedule
D64: Opening Balance | E64: [#'000] | O64: =N67 -> 649699556 | P64: =O67 -> 1007141199 | Q64: =P67 -> 1364582842 | R64: =Q67 -> 1722024485 | S64: =R67 -> 2079466128
D65: Proceeds from borrowings | E65: [#'000] | O65: =Inp!O93 -> 577322462 | P65: =Inp!P93 -> 577322462 | Q65: =Inp!Q93 -> 577322462 | R65: =Inp!R93 -> 577322462 | S65: =Inp!S93 -> 577322462
D66: Repayment of borrowings | E66: [#'000] | O66: =Inp!O94 -> -219880819 | P66: =Inp!P94 -> -219880819 | Q66: =Inp!Q94 -> -219880819 | R66: =Inp!R94 -> -219880819 | S66: =Inp!S94 -> -219880819
D67: Closing Balance | E67: [#'000] | N67: =FP!N49 -> 649699556 | O67: =SUM(O64:O66) -> 1007141199 | P67: =SUM(P64:P66) -> 1364582842 | Q67: =SUM(Q64:Q66) -> 1722024485 | R67: =SUM(R64:R66) -> 2079466128 | S67: =SUM(S64:S66) -> 2436907771
C69: Retained Earnings Schedule
D70: Drivers
D71: Dividend Payout ratio | O71: =Inp!O61 -> 0.7 | P71: =Inp!P61 -> 0.7 | Q71: =Inp!Q61 -> 0.7 | R71: =Inp!R61 -> 0.7 | S71: =Inp!S61 -> 0.7
D73: Opening Balance | E73: [#'000] | O73: =N76 -> 254002062 | P73: =O76 -> 3.0784759e+08 | Q73: =P76 -> 4.6516668e+08 | R73: =Q76 -> 8.6902214e+08 | S73: =R76 -> 1.6658515e+09
D74: Net Earnings | E74: [#'000] | O74: =IS!O30 -> 1.7948511e+08 | P74: =IS!P30 -> 5.2439696e+08 | Q74: =IS!Q30 -> 1.3461849e+09 | R74: =IS!R30 -> 2.6560979e+09 | S74: =IS!S30 -> 5.1457366e+09
D75: Dividend | E75: [#'000] | O75: =-O71*O74 -> -1.2563957e+08 | P75: =-P71*P74 -> -3.6707787e+08 | Q75: =-Q71*Q74 -> -9.423294e+08 | R75: =-R71*R74 -> -1.8592685e+09 | S75: =-S71*S74 -> -3.6020157e+09
D76: Closing Balance | E76: [#'000] | N76: =FP!N32 -> 254002062 | O76: =SUM(O73:O75) -> 3.0784759e+08 | P76: =SUM(P73:P75) -> 4.6516668e+08 | Q76: =SUM(Q73:Q75) -> 8.6902214e+08 | R76: =SUM(R73:R75) -> 1.6658515e+09 | S76: =SUM(S73:S75) -> 3.2095725e+09
C78: Recognized Reserves
D79: Recegnized Reserves | E79: [#'000] | O79: =Inp!O54 -> -943228 | P79: =Inp!P54 -> -943228 | Q79: =Inp!Q54 -> -943228 | R79: =Inp!R54 -> -943228 | S79: =Inp!S54 -> -943228
C81: Working Capital Schedule
D82: Drivers
D83: Days in a period | O83: =Inp!O65 -> 365 | P83: =Inp!P65 -> 365 | Q83: =Inp!Q65 -> 365 | R83: =Inp!R65 -> 365 | S83: =Inp!S65 -> 365
D84: Revenue | O84: =O17 -> 1.6047754e+09 | P84: =P17 -> 3.5305058e+09 | Q84: =Q17 -> 6.7079611e+09 | R84: =R17 -> 1.2745126e+10 | S84: =S17 -> 2.421574e+10
D85: Cost of Sales | O85: =O18 -> 1.235677e+09 | P85: =P18 -> 2.7184895e+09 | Q85: =Q18 -> 4.8968116e+09 | R85: =R18 -> 9.303942e+09 | S85: =S18 -> 1.767749e+10
D87: Inventory Days | E87: [Days] | O87: =Inp!O70 -> 52 | P87: =Inp!P70 -> 52 | Q87: =Inp!Q70 -> 52 | R87: =Inp!R70 -> 52 | S87: =Inp!S70 -> 52
D88: Receivables Days | E88: [Days] | O88: =Inp!O73 -> 60 | P88: =Inp!P73 -> 60 | Q88: =Inp!Q73 -> 60 | R88: =Inp!R73 -> 60 | S88: =Inp!S73 -> 60
D89: Payables Days | E89: [Days] | O89: =Inp!O106 -> 65 | P89: =Inp!P106 -> 65 | Q89: =Inp!Q106 -> 65 | R89: =Inp!R106 -> 65 | S89: =Inp!S106 -> 65
D91: Working Capital element
D92: Inventory | E92: [#'000] | N92: =FP!N19 -> 112276641 | O92: =O87/O83*O85 -> 1.7604166e+08 | P92: =P87/P83*P85 -> 3.8729165e+08 | Q92: =Q87/Q83*Q85 -> 6.9762795e+08 | R92: =R87/R83*R85 -> 1.3254931e+09 | S92: =S87/S83*S85 -> 2.5184369e+09
D93: Receivables | E93: [#'000] | N93: =FP!N20 -> 146000193 | O93: =O88/O83*O84 -> 2.6379869e+08 | P93: =P88/P83*P84 -> 5.8035712e+08 | Q93: =Q88/Q83*Q84 -> 1.1026785e+09 | R93: =R88/R83*R84 -> 2.0950892e+09 | S93: =S88/S83*S84 -> 3.9806695e+09
D94: Payables | E94: [#'000] | N94: =FP!N51 -> 49475977 | O94: =O89/O83*O85 -> 2.2005208e+08 | P94: =P89/P83*P85 -> 4.8411457e+08 | Q94: =Q89/Q83*Q85 -> 8.7203494e+08 | R94: =R89/R83*R85 -> 1.6568664e+09 | S94: =S89/S83*S85 -> 3.1480461e+09
D96: Changes in Working Capital
D97: Current Assets | N97: =N92+N93 -> 258276834 | O97: =O92+O93 -> 4.3984035e+08 | P97: =P92+P93 -> 9.6764878e+08 | Q97: =Q92+Q93 -> 1.8003065e+09 | R97: =R92+R93 -> 3.4205823e+09 | S97: =S92+S93 -> 6.4991064e+09
D98: Current Liabilities | N98: =N94 -> 49475977 | O98: =O94 -> 2.2005208e+08 | P98: =P94 -> 4.8411457e+08 | Q98: =Q94 -> 8.7203494e+08 | R98: =R94 -> 1.6568664e+09 | S98: =S94 -> 3.1480461e+09
D99: Working Capital | N99: =N97-N98 -> 208800857 | O99: =O97-O98 -> 2.1978828e+08 | P99: =P97-P98 -> 4.8353421e+08 | Q99: =Q97-Q98 -> 9.2827155e+08 | R99: =R97-R98 -> 1.7637159e+09 | S99: =S97-S98 -> 3.3510603e+09
D101: Changes in Working Capital | O101: =N99-O99 -> -10987421 | P101: =O99-P99 -> -2.6374593e+08 | Q101: =P99-Q99 -> -4.4473734e+08 | R101: =Q99-R99 -> -8.3544439e+08 | S101: =R99-S99 -> -1.5873443e+09
D103: Movement in Working Capital
D104: Inventory | E104: [#'000] | O104: =N92-O92 -> -63765020 | P104: =O92-P92 -> -2.1124999e+08 | Q104: =P92-Q92 -> -3.103363e+08 | R104: =Q92-R92 -> -6.2786516e+08 | S104: =R92-S92 -> -1.1929438e+09
D105: Receivables | E105: [#'000] | O105: =N93-O93 -> -1.177985e+08 | P105: =O93-P93 -> -3.1655843e+08 | Q105: =P93-Q93 -> -5.2232141e+08 | R105: =Q93-R93 -> -9.9241068e+08 | S105: =R93-S93 -> -1.8855803e+09
D106: Payables | E106: [#'000] | O106: =O94-N94 -> 1.705761e+08 | P106: =P94-O94 -> 2.6406249e+08 | Q106: =Q94-P94 -> 3.8792037e+08 | R106: =R94-Q94 -> 7.8483145e+08 | S106: =S94-R94 -> 1.4911798e+09
C108: Other Current Asset
D109: Other assets | E109: [#'000] | O109: =Inp!O75 -> 5155922 | P109: =Inp!P75 -> 5155922 | Q109: =Inp!Q75 -> 5155922 | R109: =Inp!R75 -> 5155922 | S109: =Inp!S75 -> 5155922
D110: Due from related parties | E110: [#'000] | O110: =Inp!O76 -> 348860131 | P110: =Inp!P76 -> 348860131 | Q110: =Inp!Q76 -> 348860131 | R110: =Inp!R76 -> 348860131 | S110: =Inp!S76 -> 348860131
C112: Non- Current Liabilities
D113: Deferred tax liabilities | E113: [#'000] | O113: =Inp!O79 -> 22306746 | P113: =Inp!P79 -> 22306746 | Q113: =Inp!Q79 -> 22306746 | R113: =Inp!R79 -> 22306746 | S113: =Inp!S79 -> 22306746
D114: Borrowings | E114: [#'000] | O114: =Inp!O80 -> 1377286 | P114: =Inp!P80 -> 1377286 | Q114: =Inp!Q80 -> 1377286 | R114: =Inp!R80 -> 1377286 | S114: =Inp!S80 -> 1377286
D115: Lease liabilities | E115: [#'000] | O115: =Inp!O81 -> 32650 | P115: =Inp!P81 -> 32650 | Q115: =Inp!Q81 -> 32650 | R115: =Inp!R81 -> 32650 | S115: =Inp!S81 -> 32650
D116: Government grants | E116: [#'000] | O116: =Inp!O82 -> 70211 | P116: =Inp!P82 -> 70211 | Q116: =Inp!Q82 -> 70211 | R116: =Inp!R82 -> 70211 | S116: =Inp!S82 -> 70211
D117: Deposit for shares | E117: [#'000] | O117: =Inp!O83 -> 0 | P117: =Inp!P83 -> 0 | Q117: =Inp!Q83 -> 0 | R117: =Inp!R83 -> 0 | S117: =Inp!S83 -> 0
C119: Currrent Liabities
D120: Contract liabilites | E120: [#'000] | O120: =Inp!O85 -> 68950583 | P120: =Inp!P85 -> 68950583 | Q120: =Inp!Q85 -> 68950583 | R120: =Inp!R85 -> 68950583 | S120: =Inp!S85 -> 68950583
D121: Current income tax payable | E121: [#'000] | O121: =Inp!O86 -> 15819889 | P121: =Inp!P86 -> 15819889 | Q121: =Inp!Q86 -> 15819889 | R121: =Inp!R86 -> 15819889 | S121: =Inp!S86 -> 15819889
D122: Lease liabilities | E122: [#'000] | O122: =Inp!O87 -> 5073 | P122: =Inp!P87 -> 5073 | Q122: =Inp!Q87 -> 5073 | R122: =Inp!R87 -> 5073 | S122: =Inp!S87 -> 5073
D123: Bank overdraft | E123: [#'000] | O123: =Inp!O88 -> 573175 | P123: =Inp!P88 -> 573175 | Q123: =Inp!Q88 -> 573175 | R123: =Inp!R88 -> 573175 | S123: =Inp!S88 -> 573175
...

Sheet Inp
A1: =Company -> BUA FOOD PLC
B3: Inputs
C5: Live Case : | I5: Start Date | L5: =K6+1 -> 44197 | M5: =L6+1 -> 44562 | N5: =M6+1 -> 44927 | O5: =N6+1 -> 45292 | P5: =O6+1 -> 45658 | Q5: =P6+1 -> 46023 | R5: =Q6+1 -> 46388 | S5: =R6+1 -> 46753
C6: Model Check : Ok | I6: End Date | K6: =EDATE(L6,-Month_in_period) -> 44196 | L6: =EDATE(M6,-Month_in_period) -> 44561 | M6: =EDATE(N6,-Month_in_period) -> 44926 | N6: =Historical_End_Date -> 45291 | O6: =EDATE(N6,Month_in_period) -> 45657 | P6: =EDATE(O6,Month_in_period) -> 46022 | Q6: =EDATE(P6,Month_in_period) -> 46387 | R6: =EDATE(Q6,Month_in_period) -> 46752 | S6: =EDATE(R6,Month_in_period) -> 47118
I7: Year | L7: =YEAR(L6) -> 2021 | M7: =YEAR(M6) -> 2022 | N7: =YEAR(N6) -> 2023 | O7: =YEAR(O6) -> 2024 | P7: =YEAR(P6) -> 2025 | Q7: =YEAR(Q6) -> 2026 | R7: =YEAR(R6) -> 2027 | S7: =YEAR(S6) -> 2028
I8: Year Counter | L8: =M8-1 -> -2 | M8: =N8-1 -> -1 | N8: 0 | O8: =N8+1 -> 1 | P8: =O8+1 -> 2 | Q8: =P8+1 -> 3 | R8: =Q8+1 -> 4 | S8: =R8+1 -> 5
D9: Description | E9: Unit
B10: Valuation Assumptions
D11: Risk Free Rate | I11: 0.20738
D12: Equity Beta | I12: 0.27439
D13: Equity Premium | I13: 0.1571
D14: Cost of Debt pre-tax | I14: 0.19
D15: Current Share Price | I15: 394.9
D16: No of Shares | I16: 18000000
D17: Terminal Growth Rate | I17: 0.07
D18: Market Cap | I18: 7110000000
D19: Debt | I19: 651076842
D20: Taxes | I20: 0.06
B22: Income Statement
C23: Above the line
D24: Revenue | E24: [year on year Growth] | L24: =IS!L11/IS!K11-1 -> 0.72805232 | M24: =IS!M11/IS!L11-1 -> 0.2552734 | N24: =IS!N11/IS!M11-1 -> 0.74362912 | O24: 1.2 | P24: 1.2 | Q24: 0.9 | R24: 0.9 | S24: 0.9
D25: Cost of sales | E25: [% of Revenue] | L25: =-IS!L12/IS!L11 -> 0.6744511 | M25: =-IS!M12/IS!M11 -> 0.67095916 | N25: =-IS!N12/IS!N11 -> 0.63448146 | O25: 0.77 | P25: 0.77 | Q25: 0.73 | R25: 0.73 | S25: 0.73
C27: Below the line
D28: Administrative expenses | E28: [% of Revenue] | L28: =-IS!L15/IS!L11 -> 0.035277535 | M28: =-IS!M15/IS!M11 -> 0.036843703 | N28: =-IS!N15/IS!N11 -> 0.019160695 | O28: 0.022 | P28: 0.022 | Q28: 0.022 | R28: 0.022 | S28: 0.022
D29: Selling and distribution expenses | E29: [% of Revenue] | L29: =-IS!L16/IS!L11 -> 0.030412672 | M29: =-IS!M16/IS!M11 -> 0.033908351 | N29: =-IS!N16/IS!N11 -> 0.04092065 | O29: 0.042 | P29: 0.042 | Q29: 0.042 | R29: 0.042 | S29: 0.042
D30: Net impairment writeback on financial assets | E30: [Ending Balance] | L30: =IS!L17 -> 143283 | M30: =IS!M17 -> 2376501 | N30: =IS!N17 -> -7890845 | O30: -7890845 | P30: -7890845 | Q30: -7890845 | R30: -7890845 | S30: -7890845
D31: Other income | E31: [% of Revenue] | L31: =IS!L18/IS!L11 -> 0.004664475 | M31: =IS!M18/IS!M11 -> 0.03643538 | N31: =IS!N18/IS!N11 -> 0.0011095104 | O31: 0.025 | P31: 0.025 | Q31: 0.025 | R31: 0.025 | S31: 0.025
D32: Depreciation | E32: [% of PPE] | L32: =-IS!L21/FP!L14 -> 0.026133886 | M32: =-IS!M21/FP!M14 -> 0.024752847 | N32: =-IS!N21/FP!N14 -> 0.026261756 | O32: 0.0265 | P32: 0.0265 | Q32: 0.0265 | R32: 0.0265 | S32: 0.0265
D33: Finance Income | E33: [Ending Balance] | L33: =IS!L24 -> 2892019 | M33: =IS!M24 -> 39721 | N33: =IS!N24 -> 2497371 | O33: 2497371 | P33: 2497371 | Q33: 2497371 | R33: 2497371 | S33: 2497371
D34: Finance Cost | E34: [Ending Balance] | L34: =IS!L25 -> -5047646 | M34: =IS!M25 -> -8721781 | N34: =IS!N25 -> -100678918 | O34: -100678918 | P34: -100678918 | Q34: -100678918 | R34: -100678918 | S34: -100678918
D35: Minimum tax | E35: [Ending Balance] | L35: =IS!L28 -> -270527 | M35: =IS!M28 -> -1580531 | N35: =IS!N28 -> -10640 | O35: -10640 | P35: -10640 | Q35: -10640 | R35: -10640 | S35: -10640
D36: Income and deferred tax expense | E36: [% of EBT] | L36: =-IS!L29/IS!L26 -> 0.099057248 | M36: =-IS!M29/IS!M26 -> 0.14599438 | N36: =IS!N29/IS!N26 -> 0.036746481 | O36: 0.06 | P36: 0.06 | Q36: 0.06 | R36: 0.06 | S36: 0.06
B38: Financial Position
C39: PPE
D40: Drivers
D41: PPE Closing Balance | L41: =FP!L14 -> 321675653 | M41: =FP!M14 -> 330523752 | N41: =FP!N14 -> 357991862
D42: Capex | L42: 107283678 | M42: 15480307 | N42: 37085853
D44: Incremental Capex | L44: =L42/L41 -> 0.33351507 | M44: =M42/M41 -> 0.046835687 | N44: =N42/N41 -> 0.10359412 | O44: 0.12 | P44: 0.12 | Q44: 0.12 | R44: 0.12 | S44: 0.12
D45: Maintenance Cape
D47: Depreciation | O47: 0.0265 | P47: 0.0265 | Q47: 0.0265 | R47: 0.0265 | S47: 0.0265
C49: Other Non-current Asset
D50: Other Non-current Asset | E50: [Ending Balance] | L50: =FP!L15 -> 1580361 | M50: =FP!M15 -> 31165 | N50: =FP!N15 -> 30324 | O50: 30324 | P50: 30324 | Q50: 30324 | R50: 30324 | S50: 30324
C52: Shareholder Equity
D53: Share capital | E53: [Ending Balance] | L53: =FP!L30 -> 9000000 | M53: =FP!M30 -> 9000000 | N53: =FP!N30 -> 9000000 | O53: 9000000 | P53: 9000000 | Q53: 9000000 | R53: 9000000 | S53: 9000000
D54: Reorganisation reserves | E54: [Ending Balance] | L54: =FP!L31 -> -943228 | M54: =FP!M31 -> -943228 | N54: =FP!N31 -> -943228 | O54: -943228 | P54: -943228 | Q54: -943228 | R54: -943228 | S54: -943228
C56: Retained Earnings
D57: Drivers
D58: Net Earnings | L58: =IS!L30 -> 69768085 | M58: =IS!M30 -> 91344019 | N58: =IS!N30 -> 112097497
D59: Dividend | M59: 63000000 | N59: 81000000
D61: Dividend Payout Ratio | L61: =L59/L58 -> 0 | M61: =M59/M58 -> 0.68970033 | N61: =N59/N58 -> 0.72258527 | O61: 0.7 | P61: 0.7 | Q61: 0.7 | R61: 0.7 | S61: 0.7
B63: Current Assets
D64: Drivers
D65: Days in in a period | L65: 365 | M65: 365 | N65: 365 | O65: 365 | P65: 365 | Q65: 365 | R65: 365 | S65: 365
D66: Revenue | L66: =IS!L11 -> 333272234 | M66: =IS!M11 -> 418347770 | N66: =IS!N11 -> 729443355
D67: Cost of Sales | L67: =-IS!L12 -> 224775825 | M67: =-IS!M12 -> 280694270 | N67: =-IS!N12 -> 462818283
D69: Inventory | L69: =FP!L19 -> 24926471 | M69: =FP!M19 -> 29760594 | N69: =FP!N19 -> 112276641
D70: Inventory Days | E70: [Days] | L70: =L69/L67*L65 -> 40.476603 | M70: =M69/M67*M65 -> 38.699104 | N70: =N69/N67*N65 -> 88.546575 | O70: 52 | P70: 52 | Q70: 52 | R70: 52 | S70: 52
D72: Trade Receivables | L72: =FP!L20 -> 48967807 | M72: =FP!M20 -> 107578798 | N72: =FP!N20 -> 146000193
D73: Trade Receivables Days | E73: [Days] | L73: =L72/L66*L65 -> 53.629579 | M73: =M72/M66*M65 -> 93.860334 | N73: =N72/N66*N65 -> 73.055804 | O73: 60 | P73: 60 | Q73: 60 | R73: 60 | S73: 60
D75: Other assets | E75: [Ending Balance] | L75: =FP!L21 -> 3192269 | M75: =FP!M21 -> 11746718 | N75: =FP!N21 -> 5155922 | O75: 5155922 | P75: 5155922 | Q75: 5155922 | R75: 5155922 | S75: 5155922
D76: Due from related parties | E76: [Ending Balance] | L76: =FP!L23 -> 162788169 | M76: =FP!M23 -> 95420170 | N76: =FP!N23 -> 348860131 | O76: 348860131 | P76: 348860131 | Q76: 348860131 | R76: 348860131 | S76: 348860131
B78: Non- Current Liabilities
D79: Deferred tax liabilities | E79: [Ending Balance] | L79: =FP!L37 -> 15225186 | M79: =FP!M37 -> 33776943 | N79: =FP!N37 -> 22306746 | O79: 22306746 | P79: 22306746 | Q79: 22306746 | R79: 22306746 | S79: 22306746
D80: Borrowings | E80: [Ending Balance] | L80: =FP!L38 -> 4889870 | M80: =FP!M38 -> 3475257 | N80: =FP!N38 -> 1377286 | O80: 1377286 | P80: 1377286 | Q80: 1377286 | R80: 1377286 | S80: 1377286
D81: Lease liabilities | E81: [Ending Balance] | L81: =FP!L39 -> 33611 | M81: =FP!M39 -> 32678 | N81: =FP!N39 -> 32650 | O81: 32650 | P81: 32650 | Q81: 32650 | R81: 32650 | S81: 32650
D82: Government grants | E82: [Ending Balance] | L82: =FP!L40 -> 0 | M82: =FP!M40 -> 206665 | N82: =FP!N40 -> 70211 | O82: 70211 | P82: 70211 | Q82: 70211 | R82: 70211 | S82: 70211
D83: Deposit for shares | E83: [Ending Balance] | L83: =FP!L41 -> 32243723 | M83: =FP!M41 -> 32243723 | N83: =FP!N41 -> 0 | O83: 0 | P83: 0 | Q83: 0 | R83: 0 | S83: 0
B84: Current Liabilities
D85: Contract liabilites | E85: [Ending Balance] | L85: =FP!L45 -> 40931459 | M85: =FP!M45 -> 47139328 | N85: =FP!N45 -> 68950583 | O85: 68950583 | P85: 68950583 | Q85: 68950583 | R85: 68950583 | S85: 68950583
D86: Current income tax payable | E86: [Ending Balance] | L86: =FP!L46 -> 12778745 | M86: =FP!M46 -> 8323257 | N86: =FP!N46 -> 15819889 | O86: 15819889 | P86: 15819889 | Q86: 15819889 | R86: 15819889 | S86: 15819889
D87: Lease liabilities | E87: [Ending Balance] | L87: =FP!L47 -> 4292441 | M87: =FP!M47 -> 5073 | N87: =FP!N47 -> 5073 | O87: 5073 | P87: 5073 | Q87: 5073 | R87: 5073 | S87: 5073
D88: Bank overdraft | E88: [Ending Balance] | L88: =FP!L48 -> 2851413 | M88: =FP!M48 -> 4490873 | N88: =FP!N48 -> 573175 | O88: 573175 | P88: 573175 | Q88: 573175 | R88: 573175 | S88: 573175
D91: Borrowings | E91: [Ending Balance] | L91: =FP!L49 -> 241159110 | M91: =FP!M49 -> 208195755 | N91: =FP!N49 -> 649699556
D92: Drivers
D93: Proceeds from borrowings | E93: [Ending Balance] | L93: 269733940 | M93: 276336593 | N93: 577322462 | O93: 577322462 | P93: 577322462 | Q93: 577322462 | R93: 577322462 | S93: 577322462
D94: Repayment from borrowings | E94: [Ending Balance] | L94: 269733940 | M94: -310410627 | N94: -219880819 | O94: -219880819 | P94: -219880819 | Q94: -219880819 | R94: -219880819 | S94: -219880819
D97: Due to related parties | E97: [Ending Balance] | L97: =FP!L50 -> 0 | M97: =FP!M50 -> 0 | N97: =FP!N50 -> 0 | O97: 0 | P97: 0 | Q97: 0 | R97: 0 | S97: 0
D98: Government grants | E98: [Ending Balance] | L98: =FP!L52 -> 0 | M98: =FP!M52 -> 48635 | N98: =FP!N52 -> 69882 | O98: 69882 | P98: 69882 | Q98: 69882 | R98: 69882 | S98: 69882
D100: Trade and other payables
D101: Drivers
D102: Days in period | L102: 365 | M102: 365 | N102: 365 | O102: 365 | P102: 365 | Q102: 365 | R102: 365 | S102: 365
D103: Cost of Sales | L103: =-IS!L12 -> 224775825 | M103: =-IS!M12 -> 280694270 | N103: =-IS!N12 -> 462818283
D105: Trade and other payables | L105: =FP!L51 -> 38345284 | M105: =FP!M51 -> 38325101 | N105: =FP!N51 -> 49475977
D106: Trade and other payables Days | E106: [Days] | L106: =L105/L103*L102 -> 62.26661 | M106: =M105/M103*M102 -> 49.835937 | N106: =N105/N103*N102 -> 39.019054 | O106: 65 | P106: 65 | Q106: 65 | R106: 65 | S106: 65

Sheet Analysis
A1: =Company -> BUA FOOD PLC
B3: Template
C5: Live Case : | I5: Start Date | O5: =N6+1 -> 44197 | P5: =O6+1 -> 44562 | Q5: =P6+1 -> 44927 | R5: =Q6+1 -> 45292 | S5: =R6+1 -> 45658 | T5: =S6+1 -> 46023 | U5: =T6+1 -> 46388 | V5: =U6+1 -> 46753
C6: Model Check : Ok | I6: End Date | N6: =EDATE(O6,-Month_in_period) -> 44196 | O6: =EDATE(P6,-Month_in_period) -> 44561 | P6: =EDATE(Q6,-Month_in_period) -> 44926 | Q6: =Historical_End_Date -> 45291 | R6: =EDATE(Q6,Month_in_period) -> 45657 | S6: =EDATE(R6,Month_in_period) -> 46022 | T6: =EDATE(S6,Month_in_period) -> 46387 | U6: =EDATE(T6,Month_in_period) -> 46752 | V6: =EDATE(U6,Month_in_period) -> 47118
I7: Year | O7: =YEAR(O6) -> 2021 | P7: =YEAR(P6) -> 2022 | Q7: =YEAR(Q6) -> 2023 | R7: =YEAR(R6) -> 2024 | S7: =YEAR(S6) -> 2025 | T7: =YEAR(T6) -> 2026 | U7: =YEAR(U6) -> 2027 | V7: =YEAR(V6) -> 2028
I8: Year Counter | O8: =P8-1 -> -2 | P8: =Q8-1 -> -1 | Q8: 0 | R8: =Q8+1 -> 1 | S8: =R8+1 -> 2 | T8: =S8+1 -> 3 | U8: =T8+1 -> 4 | V8: =U8+1 -> 5
D9: Description | E9: Unit
B12: Year | C12: Revenue | D12: COGS | E12: EBITDA | F12: EBIT | G12: NET EARNINGS | H12: TOTAL ASSET | I12: EQUITY | J12: OPERATING | K12: INVESTING | L12: FINANCING | M12: FREE
B13: 2024 | C13: 1.6047754e+09 | D13: -1.235677e+09 | E13: 2.9862125e+08 | F13: 2.8913447e+08 | G13: 1.7948511e+08 | H13: 1.6523031e+09 | I13: 3.1590437e+08 | J13: 1.7798447e+08 | K13: -42959023 | L13: 2.3180207e+08 | M13: 29678769
B14: 2025 | C14: 3.5305058e+09 | D14: -2.7184895e+09 | E14: 6.6643577e+08 | F14: 6.5606197e+08 | G14: 5.2439696e+08 | H14: 2.4311264e+09 | I14: 4.7322345e+08 | J14: 2.7102482e+08 | K14: -46975692 | L14: -9636228.3 | M14: 3.1635043e+08
B15: 2026 | C15: 6.7079611e+09 | D15: -4.8968116e+09 | E15: 1.5416482e+09 | F15: 1.5303044e+09 | G15: 1.3461849e+09 | H15: 3.5803438e+09 | I15: 8.7707891e+08 | J15: 9.1279127e+08 | K15: -51367919 | L15: -5.8488776e+08 | M15: 9.5372465e+08
B16: 2027 | C16: 1.2745126e+10 | D16: -9.303942e+09 | E16: 2.9362333e+09 | F16: 2.9238289e+09 | G16: 2.6560979e+09 | H16: 5.5194463e+09 | I16: 1.6739083e+09 | J16: 1.8330579e+09 | K16: -56170820 | L16: -1.5018269e+09 | M16: 1.8691883e+09
B17: 2028 | C17: 2.421574e+10 | D17: -1.767749e+10 | E17: 5.585945e+09 | F17: 5.5723808e+09 | G17: 5.1457366e+09 | H17: 8.9117887e+09 | I17: 3.2176293e+09 | J17: 3.5719565e+09 | K17: -61422791 | L17: -3.244574e+09 | M17: 3.602835e+09
B22: Row Labels | C22: Sum of Revenue | D22: Sum of COGS | E22: Sum of EBITDA | F22: Sum of EBIT | G22: Sum of NET EARNINGS | I22: Year | M22: REVENUE | N22: COGS | O22: EBITDA | P22: EBIT | Q22: NET P
B23: 2025 | C23: 3.5305058e+09 | D23: -2.7184895e+09 | E23: 6.6643577e+08 | F23: 6.5606197e+08 | G23: 5.2439696e+08 | I23: =B23 -> 2025 | M23: =C23 -> 3.5305058e+09 | N23: =D23 -> -2.7184895e+09 | O23: =E23 -> 6.6643577e+08 | P23: =F23 -> 6.5606197e+08 | Q23: =G23 -> 5.2439696e+08
B24: Grand Total | C24: 3.5305058e+09 | D24: -2.7184895e+09 | E24: 6.6643577e+08 | F24: 6.5606197e+08 | G24: 5.2439696e+08
B30: Row Labels | C30: Sum of TOTAL ASSET | D30: Sum of EQUITY | F30: TOTAL ASSET | G30: EQUITY
B31: 2025 | C31: 2.4311264e+09 | D31: 4.7322345e+08 | E31: =B31 -> 2025 | F31: =C31 -> 2.4311264e+09 | G31: =D31 -> 4.7322345e+08
B32: Grand Total | C32: 2.4311264e+09 | D32: 4.7322345e+08
B39: Row Labels | C39: Sum of OPERATING | D39: Sum of INVESTING | E39: Sum of FINANCING | F39: Sum of FREE | I39: OPERATING | J39: INVESTING | K39: FINANCING | L39: FREE
B40: 2025 | C40: 2.7102482e+08 | D40: -46975692 | E40: -9636228.3 | F40: 3.1635043e+08 | H40: =B40 -> 2025 | I40: =C40 -> 2.7102482e+08 | J40: =D40 -> -46975692 | K40: =E40 -> -9636228.3 | L40: =F40 -> 3.1635043e+08
B41: Grand Total | C41: 2.7102482e+08 | D41: -46975692 | E41: -9636228.3 | F41: 3.1635043e+08

Sheet Template (10)
A1: =Company -> BUA FOOD PLC
B3: Template
C5: Live Case : | I5: Start Date | L5: =K6+1 -> 44197 | M5: =L6+1 -> 44562 | N5: =M6+1 -> 44927 | O5: =N6+1 -> 45292 | P5: =O6+1 -> 45658 | Q5: =P6+1 -> 46023 | R5: =Q6+1 -> 46388 | S5: =R6+1 -> 46753
C6: Model Check : Ok | I6: End Date | K6: =EDATE(L6,-Month_in_period) -> 44196 | L6: =EDATE(M6,-Month_in_period) -> 44561 | M6: =EDATE(N6,-Month_in_period) -> 44926 | N6: =Historical_End_Date -> 45291 | O6: =EDATE(N6,Month_in_period) -> 45657 | P6: =EDATE(O6,Month_in_period) -> 46022 | Q6: =EDATE(P6,Month_in_period) -> 46387 | R6: =EDATE(Q6,Month_in_period) -> 46752 | S6: =EDATE(R6,Month_in_period) -> 47118
I7: Year | L7: =YEAR(L6) -> 2021 | M7: =YEAR(M6) -> 2022 | N7: =YEAR(N6) -> 2023 | O7: =YEAR(O6) -> 2024 | P7: =YEAR(P6) -> 2025 | Q7: =YEAR(Q6) -> 2026 | R7: =YEAR(R6) -> 2027 | S7: =YEAR(S6) -> 2028
I8: Year Counter | L8: =M8-1 -> -2 | M8: =N8-1 -> -1 | N8: 0 | O8: =N8+1 -> 1 | P8: =O8+1 -> 2 | Q8: =P8+1 -> 3 | R8: =Q8+1 -> 4 | S8: =R8+1 -> 5
D9: Description | E9: Unit
